{"adult":false,"backdrop_path":"/dAFKnTzyOBbZyRCAb33F632ctva.jpg","belongs_to_collection":null,"budget":70000000,"genres":[{"id":14,"name":"Fantastique"},{"id":18,"name":"Drame"},{"id":27,"name":"Horreur"},{"id":10749,"name":"Romance"}],"homepage":"","id":10395,"imdb_id":"tt0111742","original_language":"en","original_title":"Wolf","overview":"Will Randall, éditeur new-yorkais vieillissant et velléitaire, est sur le point de se faire renvoyer par son nouveau patron. Sa femme, Charlotte, le trompe avec un jeune arriviste qui convoite sa place. Lors d'un séjour dans le Vermont, Randall est mordu par un loup. Une péripétie dont les effets s'avèrent rapidement curieux. L'éditeur sent tous ses sens s'aiguiser et sa combativité revenir. Sous l'oeil fasciné de la fille de son intraitable patron, Laura, Randall reprend du poil de la bête, s'impose en force dans son travail, mord son rival puis, une nuit, se change carrément en loup. Le lendemain, il n'en garde aucun souvenir. Par ailleurs, une vague de meurtres ensanglante la ville...","popularity":15.244,"poster_path":"/5rDeFZZmWMq2iPJDi7zoPGgqnBZ.jpg","production_companies":[{"id":5,"logo_path":"/71BqEFAF4V3qjjMPCpLuyJFB9A.png","name":"Columbia Pictures","origin_country":"US"},{"id":215893,"logo_path":null,"name":"Douglas Wick Productions","origin_country":""}],"production_countries":[{"iso_3166_1":"US","name":"United States of America"}],"release_date":"1994-06-17","revenue":131002597,"runtime":135,"spoken_languages":[{"english_name":"English","iso_639_1":"en","name":"English"}],"status":"Released","tagline":"","title":"Wolf","video":false,"vote_average":6.105,"vote_count":851,"credits":{"cast":[{"adult":false,"gender":2,"id":514,"known_for_department":"Acting","name":"Jack Nicholson","original_name":"Jack Nicholson","popularity":32.836,"profile_path":"/b4da3H3YmAnlNCQPxdvzJfxaWXX.jpg","cast_id":1,"character":"Will Randall","credit_id":"52fe43669251416c7500ed5b","order":0},{"adult":false,"gender":1,"id":1160,"known_for_department":"Acting","name":"Michelle Pfeiffer","original_name":"Michelle Pfeiffer","popularity":38.466,"profile_path":"/oGUmQBU87QXAsnaGleYaAjAXSlj.jpg","cast_id":4,"character":"Laura Alden","credit_id":"52fe43669251416c7500ed67","order":1},{"adult":false,"gender":2,"id":13548,"known_for_department":"Acting","name":"James Spader","original_name":"James Spader","popularity":41.466,"profile_path":"/uET0mbf2bMkUXbRb1Oxi8Qjqcw3.jpg","cast_id":3,"character":"Stewart Swinton","credit_id":"52fe43669251416c7500ed63","order":2},{"adult":false,"gender":1,"id":18794,"known_for_department":"Acting","name":"Kate Nelligan","original_name":"Kate Nelligan","popularity":17.974,"profile_path":"/a2BUOy9A9WlvTfe8s4gn0MZfPa5.jpg","cast_id":12,"character":"Charlotte Randall","credit_id":"52fe43669251416c7500ed95","order":3},{"adult":false,"gender":2,"id":28633,"known_for_department":"Acting","name":"Richard Jenkins","original_name":"Richard Jenkins","popularity":26.199,"profile_path":"/muT3RZG9hiKaKojD751RcQ5tGEy.jpg","cast_id":13,"character":"Detective Carl Bridger","credit_id":"52fe43669251416c7500ed99","order":4},{"adult":false,"gender":2,"id":290,"known_for_department":"Acting","name":"Christopher Plummer","original_name":"Christopher Plummer","popularity":22.218,"profile_path":"/s5Zd3jqWfiLNGy0wQ1bDurUqN7c.jpg","cast_id":2,"character":"Raymond Alden","credit_id":"52fe43669251416c7500ed5f","order":5},{"adult":false,"gender":1,"id":20300,"known_for_department":"Acting","name":"Eileen Atkins","original_name":"Eileen Atkins","popularity":13.594,"profile_path":"/8gac03PfTFz2vByZi1aun0NiTqM.jpg","cast_id":14,"character":"Mary","credit_id":"52fe43669251416c7500ed9d","order":6},{"adult":false,"gender":2,"id":11076,"known_for_department":"Acting","name":"David Hyde Pierce","original_name":"David Hyde Pierce","popularity":12.639,"profile_path":"/9BSgq4yxjPry1Oghqq92S4wUIvs.jpg","cast_id":15,"character":"Roy McCallister","credit_id":"52fe43669251416c7500eda1","order":7},{"adult":false,"gender":2,"id":11851,"known_for_department":"Acting","name":"Om Puri","original_name":"Om Puri","popularity":8.103,"profile_path":"/3xENmjr7CA8ACRViHnjOI5jPQUt.jpg","cast_id":16,"character":"Dr. Vijay Alezais","credit_id":"52fe43669251416c7500eda5","order":8},{"adult":false,"gender":2,"id":12122,"known_for_department":"Acting","name":"Ron Rifkin","original_name":"Ron Rifkin","popularity":14.131,"profile_path":"/fj2u4t6nG0HGYFtRVDUTNbUtEtl.jpg","cast_id":17,"character":"Doctor","credit_id":"52fe43669251416c7500eda9","order":9},{"adult":false,"gender":1,"id":55643,"known_for_department":"Acting","name":"Prunella Scales","original_name":"Prunella Scales","popularity":10.338,"profile_path":"/d4LgFFrAo3O5P8FxS5d6qg6bO1E.jpg","cast_id":18,"character":"Maude Waggins","credit_id":"52fe43669251416c7500edad","order":10},{"adult":false,"gender":2,"id":28004,"known_for_department":"Acting","name":"Brian Markinson","original_name":"Brian Markinson","popularity":7.692,"profile_path":"/26fa857UrEU4aCMHVQbpvNOGuKv.jpg","cast_id":19,"character":"Detective Wade","credit_id":"52fe43669251416c7500edb1","order":11},{"adult":false,"gender":2,"id":1986,"known_for_department":"Acting","name":"Peter Gerety","original_name":"Peter Gerety","popularity":10.331,"profile_path":"/sE9fH3OxrmDflTSM3ac4ALzCjpa.jpg","cast_id":20,"character":"George","credit_id":"52fe43669251416c7500edb5","order":12},{"adult":false,"gender":2,"id":1234009,"known_for_department":"Acting","name":"Bradford English","original_name":"Bradford English","popularity":6.533,"profile_path":"/ywejaA8zuZ3MbkIm7VQdp0G2i7R.jpg","cast_id":70,"character":"Keyes","credit_id":"5cc4616d9251412ba1f985b8","order":13},{"adult":false,"gender":2,"id":80294,"known_for_department":"Acting","name":"Stewart J. Zully","original_name":"Stewart J. Zully","popularity":4.751,"profile_path":"/7NKOlWGa5SYeyrAyCLNv7WmllLT.jpg","cast_id":71,"character":"Gary","credit_id":"5cc4619a0e0a26105afd0804","order":14},{"adult":false,"gender":2,"id":46919,"known_for_department":"Acting","name":"Thomas F. Duffy","original_name":"Thomas F. Duffy","popularity":5.821,"profile_path":"/hHqrKC5fJbyxlmjIOdosMVQBcGu.jpg","cast_id":72,"character":"Tom","credit_id":"5cc461d9c3a368454a8193da","order":15},{"adult":false,"gender":0,"id":2298140,"known_for_department":"Acting","name":"Tom Oppenheim","original_name":"Tom Oppenheim","popularity":0.603,"profile_path":null,"cast_id":73,"character":"Butler","credit_id":"5cc462050e0a261a55fdadde","order":16},{"adult":false,"gender":0,"id":2298141,"known_for_department":"Acting","name":"Shirin Devrim","original_name":"Shirin Devrim","popularity":0.6,"profile_path":null,"cast_id":74,"character":"Party Guest","credit_id":"5cc4622192514151ca033432","order":17},{"adult":false,"gender":1,"id":19,"known_for_department":"Acting","name":"Allison Janney","original_name":"Allison Janney","popularity":39.096,"profile_path":"/hpBKWV1jjoXQbr1s0iUZTSvw582.jpg","cast_id":21,"character":"Party Guest","credit_id":"52fe43669251416c7500edb9","order":18},{"adult":false,"gender":0,"id":734028,"known_for_department":"Acting","name":"Kirby Mitchell","original_name":"Kirby Mitchell","popularity":4.458,"profile_path":"/4qUZtyWVPI4T2n5eALXBWdHKb3T.jpg","cast_id":75,"character":"Party Guest","credit_id":"5cc462440e0a260b0ff13ce1","order":19},{"adult":false,"gender":1,"id":195399,"known_for_department":"Acting","name":"Madhur Jaffrey","original_name":"Madhur Jaffrey","popularity":3.398,"profile_path":"/spOAkIujYaamd39H92amzj5OE8s.jpg","cast_id":76,"character":"Party Guest","credit_id":"5cc462709251415cd2f6f28c","order":20},{"adult":false,"gender":2,"id":1232496,"known_for_department":"Acting","name":"William Hill","original_name":"William Hill","popularity":7.174,"profile_path":"/ohntAmAsFUd6AkpBZtftlr1hUow.jpg","cast_id":77,"character":"Party Guest","credit_id":"5cc4629ec3a368252981752f","order":21},{"adult":false,"gender":0,"id":1400215,"known_for_department":"Acting","name":"Cynthia O'Neal","original_name":"Cynthia O'Neal","popularity":2.227,"profile_path":null,"cast_id":78,"character":"Party Guest","credit_id":"5cc462cb0e0a264509ece95e","order":22},{"adult":false,"gender":0,"id":2298142,"known_for_department":"Acting","name":"Timothy Thomas","original_name":"Timothy Thomas","popularity":1.22,"profile_path":null,"cast_id":79,"character":"Party Guest","credit_id":"5cc4630d92514151ca03355c","order":23},{"adult":false,"gender":1,"id":59201,"known_for_department":"Acting","name":"Lisa Emery","original_name":"Lisa Emery","popularity":12.718,"profile_path":"/n1BUX990xFUXtvY8fDkbUox6sHh.jpg","cast_id":80,"character":"Party Guest","credit_id":"5cc4634892514151ca033603","order":24},{"adult":false,"gender":0,"id":2298144,"known_for_department":"Acting","name":"Leigh Carlson","original_name":"Leigh Carlson","popularity":0.62,"profile_path":null,"cast_id":81,"character":"Party Guest","credit_id":"5cc46398925141257701b1b6","order":25},{"adult":false,"gender":1,"id":98729,"known_for_department":"Acting","name":"Alice Liu","original_name":"Alice Liu","popularity":3.425,"profile_path":null,"cast_id":82,"character":"Party Guest","credit_id":"5cc463ccc3a36820b5819006","order":26},{"adult":false,"gender":0,"id":2298145,"known_for_department":"Acting","name":"Max Weitzenhoffer","original_name":"Max Weitzenhoffer","popularity":0.6,"profile_path":null,"cast_id":83,"character":"Party Guest","credit_id":"5cc463f9c3a36814588b7506","order":27},{"adult":false,"gender":1,"id":9226,"known_for_department":"Acting","name":"Irene Cagen","original_name":"Irene Cagen","popularity":7.984,"profile_path":null,"cast_id":53,"character":"Office Worker","credit_id":"59ecdca6c3a3686f7000f1ac","order":28},{"adult":false,"gender":1,"id":1758640,"known_for_department":"Acting","name":"Jennifer Nicholson","original_name":"Jennifer Nicholson","popularity":1.615,"profile_path":null,"cast_id":84,"character":"Office Worker","credit_id":"5cc4644fc3a36827d583b1cd","order":29},{"adult":false,"gender":0,"id":2298146,"known_for_department":"Acting","name":"Jack Nisbet","original_name":"Jack Nisbet","popularity":0.6,"profile_path":null,"cast_id":85,"character":"Office Worker","credit_id":"5cc464769251417d390317c8","order":30},{"adult":false,"gender":0,"id":1171603,"known_for_department":"Acting","name":"Dale Kasman","original_name":"Dale Kasman","popularity":0.614,"profile_path":null,"cast_id":86,"character":"Office Worker","credit_id":"5cc464a5c3a36814588b7651","order":31},{"adult":false,"gender":0,"id":2298149,"known_for_department":"Acting","name":"Jeffrey Allen O'Den","original_name":"Jeffrey Allen O'Den","popularity":1.048,"profile_path":null,"cast_id":87,"character":"Office Worker","credit_id":"5cc464cd9251417d39031828","order":32},{"adult":false,"gender":2,"id":1315260,"known_for_department":"Acting","name":"Jose Soto","original_name":"Jose Soto","popularity":3.854,"profile_path":"/PUW8r3UER6IGuaiHFcuqKdlVnm.jpg","cast_id":88,"character":"Gang Member","credit_id":"5cc465059251412ba1f98b6f","order":33},{"adult":false,"gender":0,"id":2298150,"known_for_department":"Acting","name":"Van Bailey","original_name":"Van Bailey","popularity":0.6,"profile_path":null,"cast_id":89,"character":"Gang Member","credit_id":"5cc46550c3a36820b5819317","order":34},{"adult":false,"gender":0,"id":2298151,"known_for_department":"Acting","name":"Dwayne McClary","original_name":"Dwayne McClary","popularity":2.61,"profile_path":null,"cast_id":90,"character":"Gang Member","credit_id":"5cc465710e0a260b0ff14284","order":35},{"adult":false,"gender":0,"id":1517729,"known_for_department":"Directing","name":"Elizabeth Massie","original_name":"Elizabeth Massie","popularity":1.4,"profile_path":null,"cast_id":91,"character":"Alden's Secretary","credit_id":"5cc465dbc3a3682529817a88","order":36},{"adult":false,"gender":1,"id":154815,"known_for_department":"Acting","name":"Joanna Sanchez","original_name":"Joanna Sanchez","popularity":5.507,"profile_path":"/4Qztq8t6LJs8LofGaFgxaEOF7Dd.jpg","cast_id":92,"character":"Receptionist","credit_id":"5cc4661992514151ca033af1","order":37},{"adult":false,"gender":0,"id":1173555,"known_for_department":"Acting","name":"Eva Rodriguez","original_name":"Eva Rodriguez","popularity":0.941,"profile_path":null,"cast_id":93,"character":"Maid","credit_id":"5cc4668a0e0a261a55fdb53b","order":38},{"adult":false,"gender":1,"id":1096095,"known_for_department":"Acting","name":"Lia Chang","original_name":"Lia Chang","popularity":1.898,"profile_path":null,"cast_id":94,"character":"Desk Clerk","credit_id":"5cc466c10e0a2619d6f4785a","order":39},{"adult":false,"gender":1,"id":44822,"known_for_department":"Acting","name":"Starletta DuPois","original_name":"Starletta DuPois","popularity":3.69,"profile_path":"/pRa261QaUrK03ERYG26QHYCRP0n.jpg","cast_id":95,"character":"Victim's Mother","credit_id":"5cc466f1925141097d02d96e","order":40},{"adult":false,"gender":2,"id":90609,"known_for_department":"Directing","name":"Osgood Perkins","original_name":"Osgood Perkins","popularity":11.267,"profile_path":"/fCEfHXkvkKNPnySxlHvukgVOeTw.jpg","cast_id":96,"character":"Cop","credit_id":"5cc467449251415cd2f6f942","order":41},{"adult":false,"gender":2,"id":14409,"known_for_department":"Acting","name":"David Schwimmer","original_name":"David Schwimmer","popularity":25.708,"profile_path":"/uSFSGhvcHEg44gt3pOvtkQml6oj.jpg","cast_id":22,"character":"Cop","credit_id":"52fe43669251416c7500edbd","order":42},{"adult":false,"gender":2,"id":8855,"known_for_department":"Acting","name":"Christopher Birt","original_name":"Christopher Birt","popularity":6.24,"profile_path":null,"cast_id":97,"character":"Cop","credit_id":"5cc4679792514151ca033e1c","order":43},{"adult":false,"gender":1,"id":90196,"known_for_department":"Acting","name":"Kaity Tong","original_name":"Kaity Tong","popularity":2.45,"profile_path":null,"cast_id":98,"character":"TV Newscaster","credit_id":"5cc467e1c3a3682529817d3b","order":44},{"adult":false,"gender":1,"id":58251,"known_for_department":"Directing","name":"Elaine May","original_name":"Elaine May","popularity":5.907,"profile_path":"/vDx1oJb6UIGAVmtJ2sItcyEZG77.jpg","cast_id":99,"character":"Operator (voice) (uncredited)","credit_id":"5e79e81ea055ef001831b01b","order":45},{"adult":false,"gender":2,"id":20301,"known_for_department":"Acting","name":"Justin Kirk","original_name":"Justin Kirk","popularity":14.614,"profile_path":"/68QWfaIoOYy4QzjnjiXPXxnpT6u.jpg","cast_id":69,"character":"Laura's Brother (uncredited)","credit_id":"5caf68cdc3a3683c26aa946a","order":46}],"crew":[{"adult":false,"gender":2,"id":553,"known_for_department":"Art","name":"John Dexter","original_name":"John Dexter","popularity":2.446,"profile_path":null,"credit_id":"564e6e889251414af90010ff","department":"Art","job":"Assistant Art Director"},{"adult":false,"gender":1,"id":602,"known_for_department":"Art","name":"Linda DeScenna","original_name":"Linda DeScenna","popularity":3.866,"profile_path":null,"credit_id":"564e67829251414af7000f75","department":"Art","job":"Set Decoration"},{"adult":false,"gender":2,"id":931,"known_for_department":"Production","name":"Douglas Wick","original_name":"Douglas Wick","popularity":4.064,"profile_path":null,"credit_id":"52fe43669251416c7500ed73","department":"Production","job":"Producer"},{"adult":false,"gender":1,"id":1046,"known_for_department":"Production","name":"Juliet Taylor","original_name":"Juliet Taylor","popularity":8.006,"profile_path":"/yZpHkHDJ38MC9ochQcitEA52oFB.jpg","credit_id":"564e68d7c3a3680716001057","department":"Production","job":"Casting"},{"adult":false,"gender":2,"id":1259,"known_for_department":"Sound","name":"Ennio Morricone","original_name":"Ennio Morricone","popularity":9.286,"profile_path":"/avjgzi45bdXgC1AtyNsRc5nxtFM.jpg","credit_id":"564e68f0c3a3680716001060","department":"Sound","job":"Original Music Composer"},{"adult":false,"gender":1,"id":2242,"known_for_department":"Production","name":"Ellen Lewis","original_name":"Ellen Lewis","popularity":3.485,"profile_path":null,"credit_id":"564e6bdd9251414af5001189","department":"Production","job":"Casting"},{"adult":false,"gender":2,"id":3105,"known_for_department":"Sound","name":"Richard Portman","original_name":"Richard Portman","popularity":6.409,"profile_path":null,"credit_id":"5aeee6e00e0a261d9f004278","department":"Sound","job":"Sound Re-Recording Mixer"},{"adult":false,"gender":2,"id":3658,"known_for_department":"Production","name":"Robert Greenhut","original_name":"Robert Greenhut","popularity":1.99,"profile_path":"/ujXww2qMb8TDJ7eXuwsdgWpqUoV.jpg","credit_id":"564e6b6e9251414b010010d3","department":"Production","job":"Executive Producer"},{"adult":false,"gender":2,"id":5133,"known_for_department":"Art","name":"Bo Welch","original_name":"Bo Welch","popularity":12.984,"profile_path":"/lYSuKR7b8aNYnZmzVQh4CPk5YMe.jpg","credit_id":"564e67619251414af7000f66","department":"Art","job":"Production Design"},{"adult":false,"gender":2,"id":5342,"known_for_department":"Directing","name":"Mike Nichols","original_name":"Mike Nichols","popularity":6.494,"profile_path":"/eJgJEVil7iOJ9sTAXLCVRKfeKKM.jpg","credit_id":"52fe43669251416c7500ed6d","department":"Directing","job":"Director"},{"adult":false,"gender":2,"id":10632,"known_for_department":"Crew","name":"M. James Arnett","original_name":"M. James Arnett","popularity":4.129,"profile_path":null,"credit_id":"564e6f26c3a3680708001226","department":"Crew","job":"Stunt Coordinator"},{"adult":false,"gender":1,"id":5493,"known_for_department":"Costume & Make-Up","name":"Ann Roth","original_name":"Ann Roth","popularity":6.47,"profile_path":"/cT4EtdqvG0Yq4EQ3LASXiwyndYi.jpg","credit_id":"564e6b06c3a368070d0010f9","department":"Costume & Make-Up","job":"Costume Design"},{"adult":false,"gender":2,"id":7146,"known_for_department":"Art","name":"Tom Duffield","original_name":"Tom Duffield","popularity":3.46,"profile_path":null,"credit_id":"564e6cbcc3a368070a00112a","department":"Art","job":"Art Direction"},{"adult":false,"gender":2,"id":8880,"known_for_department":"Production","name":"Neil A. Machlis","original_name":"Neil A. Machlis","popularity":2.835,"profile_path":null,"credit_id":"564e6b7ec3a368071200106f","department":"Production","job":"Executive Producer"},{"adult":false,"gender":2,"id":12015,"known_for_department":"Editing","name":"Sam O'Steen","original_name":"Sam O'Steen","popularity":4.269,"profile_path":"/qeMnR4AX3SCoR2rK4QjXDQHpQGx.jpg","credit_id":"52fe43669251416c7500ed91","department":"Editing","job":"Editor"},{"adult":false,"gender":2,"id":16178,"known_for_department":"Costume & Make-Up","name":"Rick Baker","original_name":"Rick Baker","popularity":4.394,"profile_path":"/8thqXBS5CQF0U2zsHAVM9GH7i4I.jpg","credit_id":"5f7487ffd40d4c0037641ad8","department":"Costume & Make-Up","job":"Makeup Artist"},{"adult":false,"gender":2,"id":15318,"known_for_department":"Crew","name":"Keith Campbell","original_name":"Keith Campbell","popularity":5.641,"profile_path":"/oPAqYzvsm2m3HtnxKTuzglgFxum.jpg","credit_id":"655c25140b7316013c7c9912","department":"Crew","job":"Stunts"},{"adult":false,"gender":2,"id":15131,"known_for_department":"Camera","name":"Giuseppe Rotunno","original_name":"Giuseppe Rotunno","popularity":5.225,"profile_path":"/g983MStUH43ah1clMdObvegANEj.jpg","credit_id":"52fe43669251416c7500ed8b","department":"Camera","job":"Director of Photography"},{"adult":false,"gender":2,"id":17880,"known_for_department":"Writing","name":"Wesley Strick","original_name":"Wesley Strick","popularity":6.228,"profile_path":"/t4ggAaMWTYRtWyB1nz1BPJilujC.jpg","credit_id":"52fe43669251416c7500ed7f","department":"Writing","job":"Screenplay"},{"adult":false,"gender":2,"id":18274,"known_for_department":"Directing","name":"Michael Haley","original_name":"Michael Haley","popularity":6.075,"profile_path":"/7E5JI9exPaGp5smJV1mNdK2Rq5w.jpg","credit_id":"63484711d34eb3009037f0a4","department":"Directing","job":"First Assistant Director"},{"adult":false,"gender":2,"id":20844,"known_for_department":"Camera","name":"Giovanni Fiore Coltellacci","original_name":"Giovanni Fiore Coltellacci","popularity":1.325,"profile_path":null,"credit_id":"564e6ce2c3a368070f0010a0","department":"Camera","job":"Camera Operator"},{"adult":false,"gender":2,"id":37426,"known_for_department":"Writing","name":"Jim Harrison","original_name":"Jim Harrison","popularity":3.911,"profile_path":"/oaVbLhowYB1iDgcmh4HTZ4CUhNm.jpg","credit_id":"52fe43669251416c7500ed79","department":"Writing","job":"Screenplay"},{"adult":false,"gender":2,"id":37426,"known_for_department":"Writing","name":"Jim Harrison","original_name":"Jim Harrison","popularity":3.911,"profile_path":"/oaVbLhowYB1iDgcmh4HTZ4CUhNm.jpg","credit_id":"564e6c369251414af50011aa","department":"Production","job":"Associate Producer"},{"adult":false,"gender":1,"id":49907,"known_for_department":"Production","name":"Michele Imperato","original_name":"Michele Imperato","popularity":2.458,"profile_path":null,"credit_id":"564e6c99c3a368070f00108a","department":"Production","job":"Associate Producer"},{"adult":false,"gender":1,"id":58251,"known_for_department":"Directing","name":"Elaine May","original_name":"Elaine May","popularity":5.907,"profile_path":"/vDx1oJb6UIGAVmtJ2sItcyEZG77.jpg","credit_id":"630114c41da7a600a4ce0894","department":"Crew","job":"Additional Writing"},{"adult":false,"gender":2,"id":92377,"known_for_department":"Sound","name":"Lee Dichter","original_name":"Lee Dichter","popularity":4.68,"profile_path":null,"credit_id":"5aeee6f30e0a261d7400430b","department":"Sound","job":"Sound Re-Recording Mixer"},{"adult":false,"gender":2,"id":73951,"known_for_department":"Sound","name":"Richard P. Cirincione","original_name":"Richard P. Cirincione","popularity":2.041,"profile_path":null,"credit_id":"5aeee62cc3a3681403003782","department":"Sound","job":"Dialogue Editor"},{"adult":false,"gender":2,"id":74779,"known_for_department":"Sound","name":"Art Rochester","original_name":"Art Rochester","popularity":0.877,"profile_path":null,"credit_id":"5aeee74fc3a368142a0043d5","department":"Sound","job":"Production Sound Mixer"},{"adult":false,"gender":2,"id":99426,"known_for_department":"Sound","name":"Fred Rosenberg","original_name":"Fred Rosenberg","popularity":3.957,"profile_path":null,"credit_id":"5aeee5d49251417683004ba9","department":"Sound","job":"Dialogue Editor"},{"adult":false,"gender":1,"id":142155,"known_for_department":"Sound","name":"Laura Civiello","original_name":"Laura Civiello","popularity":2.286,"profile_path":null,"credit_id":"5aeee5be925141763e00472b","department":"Sound","job":"Dialogue Editor"},{"adult":false,"gender":1,"id":142165,"known_for_department":"Sound","name":"Suzana Peric","original_name":"Suzana Peric","popularity":5.692,"profile_path":null,"credit_id":"564e697f9251414af9000f52","department":"Sound","job":"Music Editor"},{"adult":false,"gender":2,"id":543194,"known_for_department":"Costume & Make-Up","name":"Gary Jones","original_name":"Gary Jones","popularity":1.896,"profile_path":null,"credit_id":"564e6b28c3a368071b00115b","department":"Costume & Make-Up","job":"Assistant Costume Designer"},{"adult":false,"gender":2,"id":1177850,"known_for_department":"Camera","name":"François Duhamel","original_name":"François Duhamel","popularity":2.628,"profile_path":"/3N3pFKYflQxxo3b0aRXh8adwVIU.jpg","credit_id":"564e693d9251414b0400111d","department":"Camera","job":"Still Photographer"},{"adult":false,"gender":2,"id":1308375,"known_for_department":"Sound","name":"Frank Kern","original_name":"Frank Kern","popularity":2.559,"profile_path":null,"credit_id":"5aeee7840e0a261d8c004501","department":"Sound","job":"Foley Editor"},{"adult":false,"gender":1,"id":1325235,"known_for_department":"Costume & Make-Up","name":"Cheryl Beasley Blackwell","original_name":"Cheryl Beasley Blackwell","popularity":2.477,"profile_path":null,"credit_id":"564e6a61c3a3680708001088","department":"Costume & Make-Up","job":"Costume Supervisor"},{"adult":false,"gender":2,"id":1341403,"known_for_department":"Sound","name":"Richard King","original_name":"Richard King","popularity":3.825,"profile_path":"/hjOLOjY0SIs17TxXvzb2HwIpguX.jpg","credit_id":"564e6d4a9251414af9001090","department":"Sound","job":"Sound Editor"},{"adult":false,"gender":2,"id":1392237,"known_for_department":"Art","name":"C.J. Maguire","original_name":"C.J. Maguire","popularity":1.4,"profile_path":null,"credit_id":"5aeee6420e0a261d99004285","department":"Art","job":"Property Master"},{"adult":false,"gender":1,"id":1395373,"known_for_department":"Directing","name":"Mary Bailey","original_name":"Mary Bailey","popularity":4.204,"profile_path":null,"credit_id":"564e692bc3a368070a00100f","department":"Directing","job":"Script Supervisor"},{"adult":false,"gender":2,"id":1400368,"known_for_department":"Sound","name":"Bob Olari","original_name":"Bob Olari","popularity":1.321,"profile_path":null,"credit_id":"5aeee7180e0a261d74004321","department":"Sound","job":"Sound Recordist"},{"adult":false,"gender":0,"id":1402071,"known_for_department":"Sound","name":"Bob Chefalas","original_name":"Bob Chefalas","popularity":2.054,"profile_path":null,"credit_id":"5aeee72c9251417688004bce","department":"Sound","job":"Additional Sound Re-Recording Mixer"},{"adult":false,"gender":0,"id":1403399,"known_for_department":"Crew","name":"Stan Parks","original_name":"Stan Parks","popularity":1.699,"profile_path":null,"credit_id":"564e6ef2c3a368071b001298","department":"Crew","job":"Special Effects Coordinator"},{"adult":false,"gender":0,"id":1403515,"known_for_department":"Sound","name":"Stan Bochner","original_name":"Stan Bochner","popularity":1.93,"profile_path":null,"credit_id":"564e6d259251414b070012f3","department":"Sound","job":"Supervising Sound Editor"},{"adult":false,"gender":2,"id":1403522,"known_for_department":"Sound","name":"Harry Peck Bolles","original_name":"Harry Peck Bolles","popularity":1.925,"profile_path":null,"credit_id":"5aeee5e8925141766400304b","department":"Sound","job":"Dialogue Editor"},{"adult":false,"gender":2,"id":1455292,"known_for_department":"Camera","name":"Billy Clevenger","original_name":"Billy Clevenger","popularity":0.84,"profile_path":null,"credit_id":"564e6d069251414b040012fb","department":"Camera","job":"First Assistant Camera"},{"adult":false,"gender":0,"id":1457666,"known_for_department":"Editing","name":"Kris Cole","original_name":"Kris Cole","popularity":1.518,"profile_path":null,"credit_id":"564e6a47c3a36807160010cd","department":"Editing","job":"First Assistant Editor"},{"adult":false,"gender":0,"id":1521508,"known_for_department":"Costume & Make-Up","name":"Bruce Ericksen","original_name":"Bruce Ericksen","popularity":1.357,"profile_path":null,"credit_id":"564e6ade9251414b0400125e","department":"Costume & Make-Up","job":"Costume Supervisor"},{"adult":false,"gender":0,"id":1561444,"known_for_department":"Sound","name":"Michael J. Cerone","original_name":"Michael J. Cerone","popularity":0.755,"profile_path":null,"credit_id":"5aeee7050e0a261d72003d5e","department":"Sound","job":"Sound Re-Recording Mixer"},{"adult":false,"gender":0,"id":1585001,"known_for_department":"Sound","name":"Randolph Saucedo","original_name":"Randolph Saucedo","popularity":1.772,"profile_path":null,"credit_id":"5aeee763c3a368140f0058b1","department":"Sound","job":"Sound Recordist"},{"adult":false,"gender":0,"id":1763601,"known_for_department":"Sound","name":"Stuart Stanley","original_name":"Stuart Stanley","popularity":3.344,"profile_path":null,"credit_id":"5aeee775925141768f003a73","department":"Sound","job":"Foley Editor"},{"adult":false,"gender":2,"id":1767903,"known_for_department":"Sound","name":"Michael Jacobi","original_name":"Michael Jacobi","popularity":0.869,"profile_path":null,"credit_id":"5aeee6620e0a261d760043d6","department":"Sound","job":"ADR Editor"},{"adult":false,"gender":1,"id":2493716,"known_for_department":"Crew","name":"Patricia M. Peters","original_name":"Patricia M. Peters","popularity":4.912,"profile_path":"/ogwFoDxu1sDaDFXEN6VjLF19hTC.jpg","credit_id":"63a9ddf415a4a100cb73205a","department":"Crew","job":"Stunts"},{"adult":false,"gender":0,"id":3305201,"known_for_department":"Visual Effects","name":"Ryan Berg","original_name":"Ryan Berg","popularity":0.702,"profile_path":null,"credit_id":"618d074bb076e50026291519","department":"Visual Effects","job":"Visual Effects Coordinator"}]},"keywords":{"keywords":[{"id":596,"name":"adultery"},{"id":4197,"name":"bite"},{"id":2499,"name":"heal"},{"id":7946,"name":"deer"},{"id":12564,"name":"werewolf"},{"id":156799,"name":"vermont"},{"id":188994,"name":"publisher"}]},"external_ids":{"imdb_id":"tt0111742","wikidata_id":null,"facebook_id":null,"instagram_id":null,"twitter_id":null}}