{"adult":false,"backdrop_path":"/zT9RL7opJmyCwBNxZg512Iczc2M.jpg","belongs_to_collection":null,"budget":0,"genres":[{"id":35,"name":"Comédie"}],"homepage":"","id":26271,"imdb_id":"tt0113674","original_language":"en","original_title":"Live Nude Girls","overview":"","popularity":8.995,"poster_path":"/vg9piYFtCTHep2V5EmLjwsYMzn2.jpg","production_companies":[{"id":272,"logo_path":"/5dWI6BucpMxcUdwhp2YfyGtqUPB.png","name":"Spelling Entertainment","origin_country":"US"},{"id":1930,"logo_path":null,"name":"IRS Media","origin_country":""},{"id":10348,"logo_path":null,"name":"Republic Pictures (II)","origin_country":""}],"production_countries":[{"iso_3166_1":"US","name":"United States of America"}],"release_date":"1995-12-08","revenue":0,"runtime":95,"spoken_languages":[{"english_name":"English","iso_639_1":"en","name":"English"}],"status":"Released","tagline":"","title":"Live Nude Girls","video":false,"vote_average":4.483,"vote_count":30,"credits":{"cast":[{"adult":false,"gender":1,"id":65002,"known_for_department":"Acting","name":"Dana Delany","original_name":"Dana Delany","popularity":29.165,"profile_path":"/sw49JGyGVjgtIaARlDb7c3qcAcf.jpg","cast_id":3,"character":"Jill","credit_id":"52fe44f7c3a368484e04110b","order":0},{"adult":false,"gender":1,"id":2109,"known_for_department":"Acting","name":"Kim Cattrall","original_name":"Kim Cattrall","popularity":28.86,"profile_path":"/jDqSho6MUPdlaBfS56FVNSbPyIS.jpg","cast_id":4,"character":"Jamie","credit_id":"52fe44f7c3a368484e04110f","order":1},{"adult":false,"gender":1,"id":65528,"known_for_department":"Acting","name":"Cynthia Stevenson","original_name":"Cynthia Stevenson","popularity":13.745,"profile_path":"/zdrsUVw9F0U4onvh1rS1AQor4wp.jpg","cast_id":5,"character":"Marcy","credit_id":"52fe44f7c3a368484e041113","order":2},{"adult":false,"gender":1,"id":27260,"known_for_department":"Acting","name":"Laila Robins","original_name":"Laila Robins","popularity":24.01,"profile_path":"/6ihD0IVKKKBqPO3gG3fXSiP8GMy.jpg","cast_id":6,"character":"Rachel","credit_id":"52fe44f7c3a368484e041117","order":3},{"adult":false,"gender":1,"id":94997,"known_for_department":"Acting","name":"Lora Zane","original_name":"Lora Zane","popularity":4.273,"profile_path":"/mlYJPZMmq6Uq6SNin8k9WBZ17LI.jpg","cast_id":7,"character":"Georgina","credit_id":"52fe44f7c3a368484e04111b","order":4},{"adult":false,"gender":1,"id":46423,"known_for_department":"Acting","name":"Olivia d'Abo","original_name":"Olivia d'Abo","popularity":20.095,"profile_path":"/sQTqkjNyUSl25cIDr8xhjmO4DhA.jpg","cast_id":8,"character":"Chris","credit_id":"52fe44f7c3a368484e04111f","order":5},{"adult":false,"gender":2,"id":80292,"known_for_department":"Acting","name":"Glenn Quinn","original_name":"Glenn Quinn","popularity":4.43,"profile_path":"/n8IL7WfL0c9iUDV2eWhQ5L0xveH.jpg","cast_id":9,"character":"Randy","credit_id":"52fe44f7c3a368484e041123","order":6},{"adult":false,"gender":2,"id":94998,"known_for_department":"Acting","name":"Tim Choate","original_name":"Tim Choate","popularity":5.812,"profile_path":"/tXMeNloQvJw0HPGOieWpwMieJ6K.jpg","cast_id":10,"character":"Jerome","credit_id":"52fe44f7c3a368484e041127","order":7},{"adult":false,"gender":2,"id":94999,"known_for_department":"Acting","name":"Jeremy Jordan","original_name":"Jeremy Jordan","popularity":6.233,"profile_path":"/j8OwM17P8DC4f41cvv9N8GglWXc.jpg","cast_id":11,"character":"Greenpeace Boy","credit_id":"52fe44f7c3a368484e04112b","order":8},{"adult":false,"gender":0,"id":95000,"known_for_department":"Acting","name":"Vaginal Davis","original_name":"Vaginal Davis","popularity":2.361,"profile_path":"/lCEogsizW97cFhpdgte2wkFYrGG.jpg","cast_id":12,"character":"Pool Man","credit_id":"52fe44f7c3a368484e04112f","order":9},{"adult":false,"gender":2,"id":95001,"known_for_department":"Acting","name":"Simon Templeman","original_name":"Simon Templeman","popularity":4.106,"profile_path":"/iPtoq7P82aghtPM6Bcjoj6gNBrM.jpg","cast_id":13,"character":"Bob","credit_id":"52fe44f7c3a368484e041133","order":10}],"crew":[{"adult":false,"gender":1,"id":7035,"known_for_department":"Editing","name":"Kathryn Himoff","original_name":"Kathryn Himoff","popularity":3.09,"profile_path":null,"credit_id":"56870b9bc3a368227b015f9a","department":"Editing","job":"Editor"},{"adult":false,"gender":2,"id":11799,"known_for_department":"Production","name":"Gary M. Zuckerbrod","original_name":"Gary M. Zuckerbrod","popularity":1.593,"profile_path":null,"credit_id":"56870bb6c3a368607502004c","department":"Production","job":"Casting"},{"adult":false,"gender":2,"id":10421,"known_for_department":"Art","name":"Jerry Fleming","original_name":"Jerry Fleming","popularity":2.444,"profile_path":null,"credit_id":"56870bc59251412e5201f1e6","department":"Art","job":"Production Design"},{"adult":false,"gender":1,"id":51557,"known_for_department":"Production","name":"Marcia Ross","original_name":"Marcia Ross","popularity":1.851,"profile_path":null,"credit_id":"56870baac3a3685f8900b8d9","department":"Production","job":"Casting"},{"adult":false,"gender":0,"id":94996,"known_for_department":"Writing","name":"Julianna Lavin","original_name":"Julianna Lavin","popularity":0.84,"profile_path":"/5r2OpyddqqwnS3FonKVz4TaqrNU.jpg","credit_id":"52fe44f7c3a368484e041101","department":"Directing","job":"Director"},{"adult":false,"gender":0,"id":94996,"known_for_department":"Writing","name":"Julianna Lavin","original_name":"Julianna Lavin","popularity":0.84,"profile_path":"/5r2OpyddqqwnS3FonKVz4TaqrNU.jpg","credit_id":"52fe44f7c3a368484e041107","department":"Writing","job":"Writer"},{"adult":false,"gender":2,"id":1018904,"known_for_department":"Camera","name":"Christopher Taylor","original_name":"Christopher Taylor","popularity":1.892,"profile_path":null,"credit_id":"56870b829251417e630084ec","department":"Camera","job":"Director of Photography"},{"adult":false,"gender":1,"id":1083046,"known_for_department":"Production","name":"Jeanine Rohn","original_name":"Jeanine Rohn","popularity":4.586,"profile_path":null,"credit_id":"65bd5fc4031deb0183ed748b","department":"Directing","job":"First Assistant Director"},{"adult":false,"gender":2,"id":1181479,"known_for_department":"Sound","name":"Anton Sanko","original_name":"Anton Sanko","popularity":2.228,"profile_path":null,"credit_id":"56870afec3a368607502002b","department":"Sound","job":"Original Music Composer"},{"adult":false,"gender":2,"id":1185314,"known_for_department":"Crew","name":"Jerry Spicer","original_name":"Jerry Spicer","popularity":1.873,"profile_path":null,"credit_id":"65bd5f9caf6e9401848437da","department":"Crew","job":"Stunt Coordinator"},{"adult":false,"gender":2,"id":1336197,"known_for_department":"Sound","name":"Tom Kramer","original_name":"Tom Kramer","popularity":1.612,"profile_path":null,"credit_id":"56870d1692514113340178f6","department":"Sound","job":"Music Editor"},{"adult":false,"gender":1,"id":1411258,"known_for_department":"Costume & Make-Up","name":"Linda Arnold","original_name":"Linda Arnold","popularity":1.616,"profile_path":null,"credit_id":"56870c25c3a36860e90209ae","department":"Costume & Make-Up","job":"Hair Department Head"},{"adult":false,"gender":1,"id":1415106,"known_for_department":"Sound","name":"Sarah Brady","original_name":"Sarah Brady","popularity":1.106,"profile_path":null,"credit_id":"62f7b729f92532007e9a22ca","department":"Sound","job":"ADR Supervisor"},{"adult":false,"gender":1,"id":1443038,"known_for_department":"Costume & Make-Up","name":"Zoe Hay","original_name":"Zoe Hay","popularity":2.021,"profile_path":"/tkysxV6DKeeAk9kJBFWCxPf797X.jpg","credit_id":"65bd5faeba48020182686727","department":"Costume & Make-Up","job":"Key Makeup Artist"},{"adult":false,"gender":1,"id":1532396,"known_for_department":"Sound","name":"Robin Urdang","original_name":"Robin Urdang","popularity":2.294,"profile_path":null,"credit_id":"56870cb2c3a36828f5016bd6","department":"Sound","job":"Music Supervisor"},{"adult":false,"gender":0,"id":1543451,"known_for_department":"Directing","name":"Heidi Sturdevant","original_name":"Heidi Sturdevant","popularity":0.857,"profile_path":null,"credit_id":"56870c6c9251417e1500833a","department":"Directing","job":"Script Supervisor"},{"adult":false,"gender":0,"id":1556724,"known_for_department":"Costume & Make-Up","name":"Israel Segal","original_name":"Israel Segal","popularity":0.6,"profile_path":null,"credit_id":"56870b0dc3a3685f8900b8cb","department":"Costume & Make-Up","job":"Costume Design"},{"adult":false,"gender":0,"id":1556727,"known_for_department":"Production","name":"Julie Herlocker","original_name":"Julie Herlocker","popularity":0.694,"profile_path":null,"credit_id":"56870c89c3a36828f5016bcc","department":"Production","job":"Production Coordinator"},{"adult":false,"gender":0,"id":1556728,"known_for_department":"Camera","name":"Michael Yarish","original_name":"Michael Yarish","popularity":0.6,"profile_path":null,"credit_id":"56870c9bc3a3685f8900b8f3","department":"Camera","job":"Still Photographer"},{"adult":false,"gender":0,"id":1556729,"known_for_department":"Sound","name":"Art Ford","original_name":"Art Ford","popularity":1.291,"profile_path":null,"credit_id":"56870cf4c3a368227b015fc3","department":"Sound","job":"Music Supervisor"},{"adult":false,"gender":0,"id":1556730,"known_for_department":"Sound","name":"James Dehr","original_name":"James Dehr","popularity":2.391,"profile_path":null,"credit_id":"5834da77c3a3682f2a009f9a","department":"Sound","job":"Sound Mixer"},{"adult":false,"gender":0,"id":1906096,"known_for_department":"Sound","name":"Adriane Marfiak","original_name":"Adriane Marfiak","popularity":1.303,"profile_path":null,"credit_id":"62f7b72f1cac8c007f2ee56b","department":"Sound","job":"Sound Effects Editor"},{"adult":false,"gender":0,"id":2032074,"known_for_department":"Crew","name":"Lance DeSpain","original_name":"Lance DeSpain","popularity":1.005,"profile_path":null,"credit_id":"65bd5fb8031deb0162ed735b","department":"Art","job":"Set Decoration"},{"adult":false,"gender":1,"id":2315877,"known_for_department":"Directing","name":"Suzie Pelissier","original_name":"Suzie Pelissier","popularity":1.553,"profile_path":null,"credit_id":"65bd5fd043999b00c9c3da97","department":"Directing","job":"Second Assistant Director"},{"adult":false,"gender":2,"id":2966561,"known_for_department":"Crew","name":"Jon Conrad Pochron","original_name":"Jon Conrad Pochron","popularity":1.671,"profile_path":null,"credit_id":"65bd5f8d1dbc8801491b3f27","department":"Crew","job":"Stunt Coordinator"}]},"keywords":{"keywords":[{"id":5595,"name":"sleepover"},{"id":12392,"name":"best friend"}]},"external_ids":{"imdb_id":"tt0113674","wikidata_id":null,"facebook_id":null,"instagram_id":null,"twitter_id":null}}