{"adult":false,"backdrop_path":"/blHx3LrXsIfefFggOk4gjwdX73i.jpg","belongs_to_collection":null,"budget":0,"genres":[{"id":14,"name":"Fantastique"},{"id":18,"name":"Drame"},{"id":80,"name":"Crime"}],"homepage":"","id":517839,"imdb_id":"tt5501104","original_language":"sv","original_title":"Gräns","overview":"Tina, douanière à l’efficacité redoutable, est connue pour son odorat extraordinaire. C'est presque comme si elle pouvait flairer la culpabilité d’un individu.  Mais quand Vore, un homme d'apparence suspecte, passe devant elle, ses capacités sont mises à l'épreuve pour la première fois.  Tina sait que Vore cache quelque chose, mais n’arrive pas à identifier quoi. Pire encore, elle ressent une étrange attirance pour lui...","popularity":16.091,"poster_path":"/5USITMeM29md0XqiGe0oRxjFfbd.jpg","production_companies":[{"id":108004,"logo_path":"/kvJMq7yPzXlbC6a6p3TELDfcTRD.png","name":"Meta Film Stockholm","origin_country":"SE"},{"id":110059,"logo_path":null,"name":"Black Spark Film & TV","origin_country":"SE"},{"id":2801,"logo_path":"/bswb1PLLsKDUXMLgy42bZtCtIde.png","name":"Film i Väst","origin_country":"SE"},{"id":2999,"logo_path":"/zGSqFee9aDgDuLD6vcs2mcJUem4.png","name":"SVT","origin_country":"SE"},{"id":45461,"logo_path":"/gKKOrXKD2FEemp9CkvjNy0dLWX6.png","name":"Meta Film","origin_country":"DK"},{"id":73539,"logo_path":"/fhLGxCgpAz7zWOoDz5g4FZMkFSs.png","name":"Copenhagen Film Fund","origin_country":"DK"},{"id":147232,"logo_path":null,"name":"Kärnfilm","origin_country":"SE"}],"production_countries":[{"iso_3166_1":"DK","name":"Denmark"},{"iso_3166_1":"SE","name":"Sweden"}],"release_date":"2018-09-27","revenue":2000000,"runtime":108,"spoken_languages":[{"english_name":"Swedish","iso_639_1":"sv","name":"svenska"}],"status":"Released","tagline":"Sentir quelque chose de beau.","title":"Border","video":false,"vote_average":6.71,"vote_count":757,"credits":{"cast":[{"adult":false,"gender":1,"id":132245,"known_for_department":"Acting","name":"Eva Melander","original_name":"Eva Melander","popularity":8.126,"profile_path":"/rhRJbKhetk4M9KpswhBuWcvZ7Ee.jpg","cast_id":0,"character":"Tina","credit_id":"5acf96039251413b3c000412","order":0},{"adult":false,"gender":2,"id":85751,"known_for_department":"Acting","name":"Eero Milonoff","original_name":"Eero Milonoff","popularity":6.697,"profile_path":"/2U6EPXeURLuX7zQU1gD0euS8DCP.jpg","cast_id":1,"character":"Vore","credit_id":"5acf96120e0a263473000456","order":1},{"adult":false,"gender":2,"id":1150856,"known_for_department":"Acting","name":"Jörgen Thorsson","original_name":"Jörgen Thorsson","popularity":4.586,"profile_path":"/lUBOL0RM4Q9Ree8mTc9HuDj1VwY.jpg","cast_id":6,"character":"Roland","credit_id":"5af4b3f3c3a3684713002996","order":2},{"adult":false,"gender":1,"id":73070,"known_for_department":"Acting","name":"Ann Petrén","original_name":"Ann Petrén","popularity":8.168,"profile_path":"/gs73ZPtFQ7Ei49n7vqUYFgluKiu.jpg","cast_id":53,"character":"Agneta","credit_id":"5b8ed8cd925141355e005382","order":3},{"adult":false,"gender":2,"id":6004,"known_for_department":"Acting","name":"Sten Ljunggren","original_name":"Sten Ljunggren","popularity":4.402,"profile_path":"/svT79pAbrwIot2kTVistQl232Yl.jpg","cast_id":52,"character":"Tina's Father","credit_id":"5b8ed8ab0e0a2664990062be","order":4},{"adult":false,"gender":2,"id":135695,"known_for_department":"Acting","name":"Kjell Wilhelmsen","original_name":"Kjell Wilhelmsen","popularity":3.119,"profile_path":"/ecvGG97NXVSiwPGLf1Junc287Oa.jpg","cast_id":55,"character":"Daniel","credit_id":"5b8f885e0e0a267f55009265","order":5},{"adult":false,"gender":1,"id":95907,"known_for_department":"Acting","name":"Rakel Wärmländer","original_name":"Rakel Wärmländer","popularity":4.526,"profile_path":"/5wzA7hwMRH29gBbffZVHUwcq8EB.jpg","cast_id":54,"character":"Therese","credit_id":"5b8ed8e50e0a266490006200","order":6},{"adult":false,"gender":2,"id":1090968,"known_for_department":"Acting","name":"Andreas Kundler","original_name":"Andreas Kundler","popularity":2.735,"profile_path":"/moGgEuJIybWvccLIhXXjkdV8QIJ.jpg","cast_id":7,"character":"Robert","credit_id":"5af4b405c3a3684726001375","order":7},{"adult":false,"gender":0,"id":1696065,"known_for_department":"Acting","name":"Matti Boustedt","original_name":"Matti Boustedt","popularity":1.98,"profile_path":"/8HprYfRnDw1hpv8QE8PLeZz0hOg.jpg","cast_id":51,"character":"Tomas","credit_id":"5b8578ad92514159dd056fce","order":8},{"adult":false,"gender":0,"id":1483191,"known_for_department":"Acting","name":"Tomas Åhnstrand","original_name":"Tomas Åhnstrand","popularity":1.4,"profile_path":null,"cast_id":63,"character":"Stefan","credit_id":"655bb497ea84c71094032c74","order":9},{"adult":false,"gender":1,"id":142681,"known_for_department":"Acting","name":"Josefin Neldén","original_name":"Josefin Neldén","popularity":5.743,"profile_path":"/tAEZ9ZQI6X6sfCCtmOCEjW82yYH.jpg","cast_id":64,"character":"Esther","credit_id":"655bb4ab3d745400e392ed2d","order":10},{"adult":false,"gender":0,"id":2080927,"known_for_department":"Acting","name":"Henrik Johansson","original_name":"Henrik Johansson","popularity":1.96,"profile_path":"/bB50jUtKrrEYBCAEG5sCanYXlJL.jpg","cast_id":65,"character":"Patrik","credit_id":"655bb4b87f054018d517efe2","order":11},{"adult":false,"gender":0,"id":2073620,"known_for_department":"Acting","name":"Ibrahim Faal","original_name":"Ibrahim Faal","popularity":1.473,"profile_path":null,"cast_id":66,"character":"Nursing Assistant","credit_id":"655bb50b3396b9013b379974","order":12},{"adult":false,"gender":1,"id":1308651,"known_for_department":"Acting","name":"Åsa Janson","original_name":"Åsa Janson","popularity":0.932,"profile_path":null,"cast_id":67,"character":"Nurse","credit_id":"655bb51a10923000e14322fa","order":13},{"adult":false,"gender":2,"id":1264193,"known_for_department":"Acting","name":"Donald Högberg","original_name":"Donald Högberg","popularity":3.842,"profile_path":"/sgKGp7rp3TJ17Kt5y9JhGM8nSIW.jpg","cast_id":68,"character":"Receptionist","credit_id":"655bb527ea84c710922ac348","order":14},{"adult":false,"gender":2,"id":1895104,"known_for_department":"Acting","name":"Krister Kern","original_name":"Krister Kern","popularity":2.976,"profile_path":null,"cast_id":69,"character":"Policeman","credit_id":"655bb5360b73160101ab9ee7","order":15},{"adult":false,"gender":2,"id":105465,"known_for_department":"Acting","name":"Viktor Åkerblom","original_name":"Viktor Åkerblom","popularity":3.382,"profile_path":"/qeAD9O929WUzBPFNKc7IU9fbXva.jpg","cast_id":2,"character":"Ulf","credit_id":"5acf9621c3a36873a400037c","order":16},{"adult":false,"gender":2,"id":1069785,"known_for_department":"Acting","name":"Robert Enckell","original_name":"Robert Enckell","popularity":3.475,"profile_path":"/7BbaNLsgDaICqo4YK0BdEAQXsu8.jpg","cast_id":70,"character":"Heikki","credit_id":"655bb5590816c700fd333ecd","order":17},{"adult":false,"gender":0,"id":1123775,"known_for_department":"Acting","name":"Elisabeth Göransson","original_name":"Elisabeth Göransson","popularity":1.4,"profile_path":null,"cast_id":71,"character":"Older Woman","credit_id":"655bb57aea84c710922ac35a","order":18},{"adult":false,"gender":0,"id":4166164,"known_for_department":"Acting","name":"Aksel Dis","original_name":"Aksel Dis","popularity":0.6,"profile_path":null,"cast_id":72,"character":"Anton","credit_id":"655bb5820b73160101ab9ef7","order":19},{"adult":false,"gender":0,"id":4388112,"known_for_department":"Acting","name":"Asli Dis","original_name":"Asli Dis","popularity":1.411,"profile_path":null,"cast_id":73,"character":"Anton's Mother","credit_id":"655bb58e53866e00abae4cf0","order":20},{"adult":false,"gender":0,"id":4388114,"known_for_department":"Acting","name":"Hugo Ljunggren","original_name":"Hugo Ljunggren","popularity":1.78,"profile_path":null,"cast_id":74,"character":"Teenager with a Cap","credit_id":"655bb59c10923000feade3bb","order":21},{"adult":false,"gender":0,"id":4388115,"known_for_department":"Acting","name":"Glenn Hasselberg","original_name":"Glenn Hasselberg","popularity":0.6,"profile_path":null,"cast_id":75,"character":"Bartender","credit_id":"655bb5a853866e00e295c4e7","order":22},{"adult":false,"gender":0,"id":4388116,"known_for_department":"Acting","name":"Isra Nur","original_name":"Isra Nur","popularity":1.4,"profile_path":null,"cast_id":76,"character":"Cashier","credit_id":"655bb5b20816c70137ebaf94","order":23},{"adult":false,"gender":0,"id":3128958,"known_for_department":"Acting","name":"Åsa Johansson","original_name":"Åsa Johansson","popularity":1.4,"profile_path":null,"cast_id":77,"character":"Ambulance Nurse","credit_id":"655bb5bf53866e011c0a68f9","order":24},{"adult":false,"gender":2,"id":2141745,"known_for_department":"Acting","name":"Kardo Razzazi","original_name":"Kardo Razzazi","popularity":12.413,"profile_path":"/98ORKOZFDEDjutqAcARyr4ITE8K.jpg","cast_id":78,"character":"Voice 1 (voice)","credit_id":"655bb5eb7f054018d6f54426","order":25},{"adult":false,"gender":1,"id":367681,"known_for_department":"Acting","name":"Natalie Minnevik","original_name":"Natalie Minnevik","popularity":2.313,"profile_path":"/nFvMXkDaIePUhwaFkSo1gqiqCHt.jpg","cast_id":79,"character":"Voice 2 (voice)","credit_id":"655bb5f17f054018d517f03a","order":26},{"adult":false,"gender":0,"id":2040605,"known_for_department":"Acting","name":"Joakim Olsson","original_name":"Joakim Olsson","popularity":1.708,"profile_path":null,"cast_id":46,"character":"Tourist (uncredited)","credit_id":"5af57d749251415133005009","order":27}],"crew":[{"adult":false,"gender":1,"id":42099,"known_for_department":"Production","name":"Meta Louise Foldager","original_name":"Meta Louise Foldager","popularity":3.329,"profile_path":null,"credit_id":"5af57b569251415129003c4f","department":"Production","job":"Executive Producer"},{"adult":false,"gender":2,"id":57016,"known_for_department":"Production","name":"Tomas Eskilsson","original_name":"Tomas Eskilsson","popularity":2.471,"profile_path":"/8kcMhpCdESGgYotKPa98tsidC2C.jpg","credit_id":"5ebc7fd7076ce800217361af","department":"Production","job":"Executive Producer"},{"adult":false,"gender":2,"id":74397,"known_for_department":"Writing","name":"John Ajvide Lindqvist","original_name":"John Ajvide Lindqvist","popularity":5.512,"profile_path":"/7L9xzp795Cv1uZFTrkavKl09Rj2.jpg","credit_id":"5af7581fc3a3682aac0012c2","department":"Writing","job":"Screenplay"},{"adult":false,"gender":2,"id":74397,"known_for_department":"Writing","name":"John Ajvide Lindqvist","original_name":"John Ajvide Lindqvist","popularity":5.512,"profile_path":"/7L9xzp795Cv1uZFTrkavKl09Rj2.jpg","credit_id":"5af7579dc3a3682ab30024fe","department":"Writing","job":"Short Story"},{"adult":false,"gender":2,"id":105468,"known_for_department":"Production","name":"Peter Gustafsson","original_name":"Peter Gustafsson","popularity":2.279,"profile_path":null,"credit_id":"5af57b0c9251415142004fb5","department":"Production","job":"Producer"},{"adult":false,"gender":2,"id":557759,"known_for_department":"Crew","name":"Kimmo Rajala","original_name":"Kimmo Rajala","popularity":3.979,"profile_path":"/jkAWBWKOFQfdAMRqxTxGs7jmjJ7.jpg","credit_id":"5af57cfbc3a3682a6c006bdd","department":"Crew","job":"Stunt Coordinator"},{"adult":false,"gender":1,"id":1038996,"known_for_department":"Production","name":"Sara Törnkvist","original_name":"Sara Törnkvist","popularity":2.18,"profile_path":null,"credit_id":"5af57bb1c3a3682a7500433d","department":"Production","job":"Casting"},{"adult":false,"gender":0,"id":1155570,"known_for_department":"Production","name":"Petra Jönsson","original_name":"Petra Jönsson","popularity":1.96,"profile_path":null,"credit_id":"5af57b180e0a264269003e1d","department":"Production","job":"Producer"},{"adult":false,"gender":2,"id":1280827,"known_for_department":"Crew","name":"Lars Hjelm","original_name":"Lars Hjelm","popularity":2.416,"profile_path":null,"credit_id":"5af57cf0c3a3682a80002728","department":"Crew","job":"Stunts"},{"adult":false,"gender":0,"id":1346222,"known_for_department":"Production","name":"Louis Tisné","original_name":"Louis Tisné","popularity":1.96,"profile_path":null,"credit_id":"5af57b660e0a26426c004cb5","department":"Production","job":"Executive Producer"},{"adult":false,"gender":0,"id":1365202,"known_for_department":"Production","name":"Nina Bisgaard","original_name":"Nina Bisgaard","popularity":3.149,"profile_path":null,"credit_id":"5af57afdc3a3682a5f0053d6","department":"Production","job":"Producer"},{"adult":false,"gender":2,"id":1400327,"known_for_department":"Visual Effects","name":"Peter Hjorth","original_name":"Peter Hjorth","popularity":6.762,"profile_path":null,"credit_id":"5af57ccf0e0a264257004ae4","department":"Visual Effects","job":"Visual Effects Supervisor"},{"adult":false,"gender":2,"id":1400327,"known_for_department":"Visual Effects","name":"Peter Hjorth","original_name":"Peter Hjorth","popularity":6.762,"profile_path":null,"credit_id":"5af57c520e0a265560003dd7","department":"Directing","job":"Second Unit Director"},{"adult":false,"gender":0,"id":1403748,"known_for_department":"Sound","name":"Anders Kwarnmark","original_name":"Anders Kwarnmark","popularity":1.8,"profile_path":null,"credit_id":"5af57c900e0a264251004511","department":"Sound","job":"Sound Effects Editor"},{"adult":false,"gender":1,"id":1425110,"known_for_department":"Editing","name":"Olivia Neergaard-Holm","original_name":"Olivia Neergaard-Holm","popularity":1.62,"profile_path":null,"credit_id":"5af57b9ac3a3682a7500432d","department":"Editing","job":"Editor"},{"adult":false,"gender":2,"id":1428529,"known_for_department":"Sound","name":"Lucas Nilsson","original_name":"Lucas Nilsson","popularity":1.694,"profile_path":null,"credit_id":"5af57cb1c3a3682a6c006bb3","department":"Sound","job":"Foley Artist"},{"adult":false,"gender":2,"id":1574550,"known_for_department":"Directing","name":"Ali Abbasi","original_name":"Ali Abbasi","popularity":3.62,"profile_path":"/1mwdpvwjAG1NkvUwpdBMEMJnjK2.jpg","credit_id":"5af7585f9251412c6a0028a3","department":"Writing","job":"Screenplay"},{"adult":false,"gender":2,"id":1574550,"known_for_department":"Directing","name":"Ali Abbasi","original_name":"Ali Abbasi","popularity":3.62,"profile_path":"/1mwdpvwjAG1NkvUwpdBMEMJnjK2.jpg","credit_id":"5acf96310e0a2634640004a9","department":"Directing","job":"Director"},{"adult":false,"gender":1,"id":1594191,"known_for_department":"Costume & Make-Up","name":"Pamela Goldammer","original_name":"Pamela Goldammer","popularity":3.167,"profile_path":null,"credit_id":"5c6f74270e0a2623acd3de69","department":"Costume & Make-Up","job":"Makeup Designer"},{"adult":false,"gender":2,"id":1610512,"known_for_department":"Sound","name":"Erik Bjerknes","original_name":"Erik Bjerknes","popularity":1.094,"profile_path":null,"credit_id":"5af57c830e0a26424800448c","department":"Sound","job":"Sound"},{"adult":false,"gender":0,"id":1611880,"known_for_department":"Camera","name":"Nadim Carlsen","original_name":"Nadim Carlsen","popularity":0.764,"profile_path":null,"credit_id":"5af57b8f0e0a26426c004cca","department":"Camera","job":"Director of Photography"},{"adult":false,"gender":0,"id":1611881,"known_for_department":"Editing","name":"Anders Skov","original_name":"Anders Skov","popularity":1.4,"profile_path":null,"credit_id":"5af57ba70e0a264269003e48","department":"Editing","job":"Editor"},{"adult":false,"gender":2,"id":1620820,"known_for_department":"Costume & Make-Up","name":"Pierre Olivier Persin","original_name":"Pierre Olivier Persin","popularity":2.557,"profile_path":"/otVgM9ngvMjHYb9WNdR55eLUyYX.jpg","credit_id":"5af57c269251415129003c9b","department":"Costume & Make-Up","job":"Prosthetic Makeup Artist"},{"adult":false,"gender":2,"id":1630491,"known_for_department":"Production","name":"Mikael Windelin","original_name":"Mikael Windelin","popularity":3.085,"profile_path":null,"credit_id":"5af57ce10e0a26426c004d81","department":"Visual Effects","job":"Visual Effects Producer"},{"adult":false,"gender":2,"id":1630491,"known_for_department":"Production","name":"Mikael Windelin","original_name":"Mikael Windelin","popularity":3.085,"profile_path":null,"credit_id":"5af57b77c3a3682a8a004f46","department":"Production","job":"Post Producer"},{"adult":false,"gender":1,"id":1851302,"known_for_department":"Production","name":"Eva Åkergren","original_name":"Eva Åkergren","popularity":2.068,"profile_path":null,"credit_id":"5af57b819251415147004e87","department":"Production","job":"Line Producer"},{"adult":false,"gender":0,"id":1887425,"known_for_department":"Production","name":"Emil Wiklund","original_name":"Emil Wiklund","popularity":1.015,"profile_path":null,"credit_id":"5af57d5392514151620045a6","department":"Crew","job":"Legal Services"},{"adult":false,"gender":0,"id":1906306,"known_for_department":"Directing","name":"Rikard Waxin","original_name":"Rikard Waxin","popularity":1.183,"profile_path":null,"credit_id":"5af57c750e0a26424b004317","department":"Directing","job":"First Assistant Director"},{"adult":false,"gender":1,"id":1932374,"known_for_department":"Directing","name":"Isabella Eklöf","original_name":"Isabella Eklöf","popularity":2.791,"profile_path":"/rmUwTPTmei0M1VMKNN0vE67gXNE.jpg","credit_id":"5af757b00e0a26559e0020cb","department":"Writing","job":"Screenplay"},{"adult":false,"gender":2,"id":1969393,"known_for_department":"Sound","name":"Jesper Miller","original_name":"Jesper Miller","popularity":2.072,"profile_path":null,"credit_id":"5af57ca79251416a77003ce2","department":"Sound","job":"Sound Mixer"},{"adult":false,"gender":2,"id":1973132,"known_for_department":"Sound","name":"Martin Juel Dirkov","original_name":"Martin Juel Dirkov","popularity":1.38,"profile_path":null,"credit_id":"5c0f3b0a9251414f2903b68c","department":"Sound","job":"Original Music Composer"},{"adult":false,"gender":0,"id":1977285,"known_for_department":"Sound","name":"Rune Sand","original_name":"Rune Sand","popularity":1.166,"profile_path":null,"credit_id":"5af57cbd9251416a77003ce8","department":"Sound","job":"Sound Effects Editor"},{"adult":false,"gender":2,"id":1985798,"known_for_department":"Camera","name":"Benjamin Zadig","original_name":"Benjamin Zadig","popularity":1.4,"profile_path":null,"credit_id":"5af57d3cc3a3682a8a005032","department":"Camera","job":"First Assistant Camera"},{"adult":false,"gender":0,"id":1999128,"known_for_department":"Costume & Make-Up","name":"Erica Spetzig","original_name":"Erica Spetzig","popularity":3.079,"profile_path":null,"credit_id":"5af57c32925141698d00390b","department":"Costume & Make-Up","job":"Makeup Designer"},{"adult":false,"gender":0,"id":2040593,"known_for_department":"Costume & Make-Up","name":"Elsa Fischer","original_name":"Elsa Fischer","popularity":1.048,"profile_path":null,"credit_id":"5c0f3b839251414f2903b6e5","department":"Costume & Make-Up","job":"Costume Design"},{"adult":false,"gender":2,"id":2040594,"known_for_department":"Costume & Make-Up","name":"Göran Lundström","original_name":"Göran Lundström","popularity":2.744,"profile_path":null,"credit_id":"5c6f740b9251410db77c58dd","department":"Costume & Make-Up","job":"Makeup Designer"},{"adult":false,"gender":0,"id":2040595,"known_for_department":"Costume & Make-Up","name":"Cristina Malillos","original_name":"Cristina Malillos","popularity":2.268,"profile_path":null,"credit_id":"5af57c189251415154003ab2","department":"Costume & Make-Up","job":"Special Effects Makeup Artist"},{"adult":false,"gender":0,"id":2040596,"known_for_department":"Production","name":"Lejla Besic","original_name":"Lejla Besic","popularity":1.4,"profile_path":null,"credit_id":"5af57c429251415162004530","department":"Production","job":"Production Manager"},{"adult":false,"gender":0,"id":2040597,"known_for_department":"Directing","name":"Erik Lövoll","original_name":"Erik Lövoll","popularity":1.4,"profile_path":null,"credit_id":"5af57c61925141515a003d11","department":"Directing","job":"Second Assistant Director"},{"adult":false,"gender":0,"id":2040600,"known_for_department":"Sound","name":"Erik Löderstedt","original_name":"Erik Löderstedt","popularity":1.052,"profile_path":null,"credit_id":"5af57c9a0e0a26425900460e","department":"Sound","job":"Boom Operator"},{"adult":false,"gender":2,"id":2040601,"known_for_department":"Crew","name":"Victor Rajala","original_name":"Victor Rajala","popularity":1.422,"profile_path":null,"credit_id":"5af57d08c3a3682a84005390","department":"Crew","job":"Stunts"},{"adult":false,"gender":0,"id":2040602,"known_for_department":"Camera","name":"André Ferreira Barbosa","original_name":"André Ferreira Barbosa","popularity":1.4,"profile_path":null,"credit_id":"5af57d1b0e0a2642590046f1","department":"Camera","job":"Second Assistant Camera"},{"adult":false,"gender":0,"id":2040603,"known_for_department":"Camera","name":"Björn Liljegrääs","original_name":"Björn Liljegrääs","popularity":0.6,"profile_path":null,"credit_id":"5af57d2c0e0a2642590046fd","department":"Camera","job":"Digital Imaging Technician"},{"adult":false,"gender":0,"id":2040604,"known_for_department":"Art","name":"Richard Johansen","original_name":"Richard Johansen","popularity":1.018,"profile_path":null,"credit_id":"5af57d470e0a264261004727","department":"Art","job":"Location Scout"},{"adult":false,"gender":0,"id":2192829,"known_for_department":"Sound","name":"Christoffer Berg","original_name":"Christoffer Berg","popularity":1.38,"profile_path":null,"credit_id":"5c0f3ae9c3a368252d0d97d6","department":"Sound","job":"Original Music Composer"},{"adult":false,"gender":0,"id":2192830,"known_for_department":"Art","name":"Frida Hoas","original_name":"Frida Hoas","popularity":1.579,"profile_path":null,"credit_id":"5c0f3ba40e0a2638c50dc153","department":"Art","job":"Production Design"}]},"keywords":{"keywords":[{"id":2337,"name":"pedophilia"},{"id":1192,"name":"sweden"},{"id":6152,"name":"supernatural"},{"id":6443,"name":"child pornography"},{"id":11264,"name":"border guard"},{"id":156866,"name":"based on short story"},{"id":163080,"name":"finland"}]},"external_ids":{"imdb_id":"tt5501104","wikidata_id":"Q53736577","facebook_id":null,"instagram_id":null,"twitter_id":null}}