{"adult":false,"also_known_as":["Стэнли Кубрик","ستانلي كوبريك","스탠리 큐브릭","スタンリー・キューブリック","สแตนลีย์ คูบริก","斯坦利·库布里克","Стенли Кубрик","اِستانلی کوبریک","स्टैनली कूब्रिक"],"biography":"Stanley Kubrick est un réalisateur, photographe, scénariste et producteur de cinéma américain, né le 26 juillet 1928 à Manhattan (New York) et mort le 7 mars 1999 dans son manoir de Childwickbury, entre St Albans et Harpenden (Hertfordshire, au nord de Londres).\n\nAprès des débuts dans la photographie, Kubrick, autodidacte, est également son propre directeur de la photographie, producteur, scénariste et monteur. Ses treize longs métrages en quarante-six ans de carrière l'imposent comme l'un des cinéastes majeurs du XXe siècle. Quatre de ses films sont classés dans le Top 100 de l'American Film Institute (AFI's 100 Years...100 Movies).\n\nStanley Kubrick est issu d'une famille juive originaire d'Europe centrale habitant dans le quartier du Bronx. Il est le fils de Sadie Gertrude Perveler (1903-1985) et de Jacob Leonard Kubrick (1901-1985). Son père, né aux États-Unis d'une mère roumaine et d'un père austro-hongrois, était cardiologue, pianiste et photographe amateur. Il apprend à son fils Stanley, âgé de douze ans, à jouer aux échecs. Cette passion suit Stanley Kubrick toute sa vie. Sa mère, qui était chanteuse et danseuse, lui donne le goût des livres et de la lecture. Il a une sœur cadette, Barbara, née le 21 mai 1934.\n\nDe 1940 à 1945, Kubrick ne trouve aucun intérêt à l'école: à part la physique rien ne l'intéresse. Il ne parvient pas à obtenir une moyenne suffisante pour s'inscrire à l'université, surtout que, la guerre terminée, nombre de soldats revenant du front tentent d'y entrer et que déjà les inscriptions sont limitées.\n\nEn 1947, à l'âge de 18 ans, il se marie avec Toba Metz, une camarade de classe de la William Howard Taft High School à New York. Ils s'installent dans le quartier de Greenwich Village deux ans plus tard et divorcent en 1951.\n\nPour son treizième anniversaire, son père lui offre son premier appareil photo. Cette nouvelle activité le passionne et lui fait oublier sa passion de jeunesse, le jazz, et son rêve de devenir batteur de jazz professionnel. Il prend de nombreuses photos et les développe avec un ami dans la chambre noire familiale. Il devient le photographe officiel de son collège et a pour idole le reporter-photographe Weegee.\n\nEn avril 1945, à l'âge de 16 ans, il réussit à vendre au magazine illustré Look une photographie d'un vendeur de journaux en larmes après la mort de Franklin D. Roosevelt, qu'il a prise alors qu'il se rendait à l'école. La rédactrice en chef l'engage comme photographe indépendant, «par pitié» dit-il plus tard. Stanley Kubrick y travaille durant quatre ans et y apprend les ficelles du métier, la composition d'une image, les éclairages, l'usage des extérieurs et l'art de saisir le mouvement. Plutôt perfectionniste, il lui arrive de prendre plusieurs centaines de clichés pour réaliser une seule photo. Grand amateur de boxe, son premier «photos-récit» intitulé Prizefighter (Le Professionnel) raconte une journée de la vie du boxeur Walter Cartier. C'est ce photo-récit qui est à l'origine de son premier film: Day of the Fight. ...\n\nSource: Article \"Stanley Kubrick\" de Wikipédia en français, soumis à la licence CC-BY-SA 3.0.","birthday":"1928-07-26","deathday":"1999-03-07","gender":2,"homepage":null,"id":240,"imdb_id":"nm0000040","known_for_department":"Directing","name":"Stanley Kubrick","place_of_birth":"New York City, New York, USA","popularity":21.761,"profile_path":"/yFT0VyIelI9aegZrsAwOG5iVP4v.jpg","credits":{"cast":[{"adult":false,"backdrop_path":"/kLyCPcXKK4M3cvjyTVGsiaLHvz1.jpg","genre_ids":[99],"id":2740,"original_language":"fr","original_title":"Opération Lune","overview":"Opération Lune est un canular sous forme de documentaire réalisé par William Karel en 2002.Un documentaire d'intrigue, subtil mélange de faits réels, de fiction et d'hypothèses autour d'un événement qui marqua le XXe siècle : la course à la Lune. Richard Nixon était-il prêt à tout pour assurer la suprématie des États-Unis dans la conquête de l'espace ? Y a-t-il vraiment eu des « retransmissions en direct » de la Lune ? Quels liens Stanley Kubrick entretenait-il avec la Nasa ? Construit autour de réelles interviews d'Henry Kissinger, Donald Rumsfeld ou Buzz Aldrin, ce film jette le trouble et nous rappelle le pouvoir des images et leur possible manipulation.","popularity":7.867,"poster_path":"/laXbmxysfDhoiUThpS5mFKlrP1R.jpg","release_date":"2002-10-16","title":"Opération Lune","video":false,"vote_average":7.0,"vote_count":37,"character":"Self (archive footage)","credit_id":"52fe4369c3a36847f80523d9","order":10},{"adult":false,"backdrop_path":"/lt1Lan9bmG29JjqaMad5tkRpCHJ.jpg","genre_ids":[99],"id":45966,"original_language":"en","original_title":"Day of the Fight","overview":"Interesting little short that works thanks to its pacing and shot variety.","popularity":6.857,"poster_path":"/4caX3IZkf7n2QCbxaJO3hyn0SCm.jpg","release_date":"1951-04-26","title":"Day of the Fight","video":false,"vote_average":5.771,"vote_count":146,"character":"Self (man at ringside with camera) (uncredited)","credit_id":"52fe46dcc3a36847f8116603","order":5},{"adult":false,"backdrop_path":"/m8PPjY6igKfsMp0wZC1JtmMRgTT.jpg","genre_ids":[99],"id":18875,"original_language":"en","original_title":"Making 'The Shining'","overview":"","popularity":8.469,"poster_path":"/upBsuweJjBftrkJGqVf8PHCdH0l.jpg","release_date":"1980-10-04","title":"Making 'The Shining'","video":false,"vote_average":7.1,"vote_count":102,"character":"Self","credit_id":"52fe47a49251416c750a097b","order":3},{"adult":false,"backdrop_path":"/2Rx61lWWkxR0jeaBi0H0CJQm35b.jpg","genre_ids":[99],"id":30416,"original_language":"en","original_title":"Stanley Kubrick: A Life in Pictures","overview":"Un documentaire sur l'univers mystérieux d'un des génies du septième art avec en voix off Tom Cruise. Inspiré des archives de la famille Kubrick, ce long métrage dresse le portrait intimiste d'une figure de légende à travers des images fascinantes (Stanley Kubrick à ses débuts, sur les plateaux de tournage et dans la vie privée) et commentées par ses collaborateurs, collègues et amis. Depuis ses choix musicaux jusqu'à ses angles de caméra en passant par ses projets restés inachevés, il s'agit d'un document essentiel à la compréhension de l'homme et de ses oeuvres.","popularity":10.445,"poster_path":"/yGrzFNyc9ztyAJejneh9734Y9Uj.jpg","release_date":"2001-05-02","title":"Stanley Kubrick: A Life in Pictures","video":false,"vote_average":7.4,"vote_count":180,"character":"Self (archive footage)","credit_id":"564166dd92514128a9001470","order":0},{"adult":false,"backdrop_path":"/mKEmuB7diOa7Ef0tJSGQ3fYJnNe.jpg","genre_ids":[18,10752],"id":600,"original_language":"en","original_title":"Full Metal Jacket","overview":"Pendant la guerre du Viêt Nam, la préparation et l’entraînement d’un groupe de jeunes marines, jusqu’au terrible baptême du feu et la sanglante offensive du Tết à Hue, en 1968.","popularity":42.983,"poster_path":"/cShwwkz4gBBIRj8yFy8TP2tEWZ4.jpg","release_date":"1987-06-26","title":"Full Metal Jacket","video":false,"vote_average":8.133,"vote_count":10126,"character":"Murphy (voice) (uncredited)","credit_id":"570a82529251417da7000201","order":59},{"adult":false,"backdrop_path":null,"genre_ids":[99],"id":315467,"original_language":"en","original_title":"Kubrick Remembered","overview":"","popularity":4.743,"poster_path":"/w4RlExGY9Z78PnxoWfEegQmLAIt.jpg","release_date":"2014-11-04","title":"Kubrick Remembered","video":false,"vote_average":6.5,"vote_count":12,"character":"Self (archive footage)","credit_id":"58452607c3a36847f9013bff","order":4},{"adult":false,"backdrop_path":"/mMNamhKWDeddUOi4W1JqBMro1ng.jpg","genre_ids":[99],"id":458080,"original_language":"en","original_title":"Filmworker","overview":"","popularity":9.321,"poster_path":"/qmZDdrb0nwrV6UMNQQWQh60t7pq.jpg","release_date":"2018-05-11","title":"Filmworker","video":false,"vote_average":7.007,"vote_count":70,"character":"Self (archive footage)","credit_id":"5bffb0319251417e2e00683c","order":1},{"adult":false,"backdrop_path":"/2fwPrfty54UycbtWakUK1Y95eoA.jpg","genre_ids":[99],"id":333275,"original_language":"fr","original_title":"Il était une fois… Orange Mécanique","overview":"Stanley Kubrick tourne Orange mécanique en 1971. Sur fond de délinquance juvénile, le film dénonce les techniques de conditionnement mental utilisées pour redresser les déviances. Censé se dérouler dans un futur proche, il est très ancré dans la fin des années soixante, marquée par la contestation anti-autoritaire des institutions et la montée de l'insécurité urbaine. Orange mécanique reste l'œuvre choc d'un visionnaire.","popularity":2.36,"poster_path":"/qr3MW5UVWzlQhuKnOH4UY0ltfDV.jpg","release_date":"2012-12-01","title":"Il était une fois… Orange Mécanique","video":false,"vote_average":7.0,"vote_count":9,"character":"Self (archive footage)","credit_id":"5c92c3550e0a261053e75636","order":0},{"adult":false,"backdrop_path":"/2crppCyt7kzzxyQXM1PnyD1Q0Sf.jpg","genre_ids":[99],"id":615434,"original_language":"en","original_title":"Trumbull Land","overview":"De \"2001, l'Odyssée de l'espace\", en 1968, à \"Tree of Life\", en 2011, Douglas Trumbull est un maître des effets spéciaux visuels, l'un des précurseurs du cinéma immersif. Aujourd'hui, à plus de 75 ans, passionné par les développements des nouvelles technologies et de la réalité virtuelle, il poursuit ses recherches en véritable artisan.","popularity":5.413,"poster_path":"/ueqsk74i06NLLw2o3eW4nyyOj2L.jpg","release_date":"2018-10-15","title":"Douglas Trumbull : L'illusionniste du cinéma","video":false,"vote_average":7.6,"vote_count":7,"character":"Self (archive footage)","credit_id":"5d2b1419a294f00010320e8d","order":1},{"adult":false,"backdrop_path":"/pyR9Dq5JKMPAUo306ahhdpK6Mbh.jpg","genre_ids":[99],"id":494676,"original_language":"en","original_title":"'2001: A Space Odyssey' – A Look Behind the Future","overview":"","popularity":3.14,"poster_path":"/pLwbiU2KTYQjN6KrSuX4IFHBdS5.jpg","release_date":"1966-01-01","title":"'2001: A Space Odyssey' – A Look Behind the Future","video":false,"vote_average":6.5,"vote_count":9,"character":"Self","credit_id":"5d9919f8aaec71001a68e00a","order":4},{"adult":false,"backdrop_path":"/5nldLwu77WjpvoeQJU426OWCtZ7.jpg","genre_ids":[99],"id":689705,"original_language":"fr","original_title":"Kubrick by Kubrick","overview":"Stanley Kubrick s'exprimait peu. Ce documentaire envoûtant fait entendre la parole rare d'un cinéaste aussi génial que secret, au travers des entretiens qu'il a accordés au critique de cinéma Michel Ciment. Inspirés des célèbres travellings de Kubrick, de lents mouvements de caméra nous promènent dans un musée labyrinthique, au décor inspiré de \"2001 : l'odyssée de l'espace\".","popularity":8.801,"poster_path":"/zZvNe2Qu4YTXiQzssiuhwgSwjpJ.jpg","release_date":"2020-10-22","title":"Kubrick par Kubrick","video":false,"vote_average":7.5,"vote_count":33,"character":"Self (archive footage)","credit_id":"5ec2c79018b751001ec90c6b","order":0},{"adult":false,"backdrop_path":null,"genre_ids":[18,14],"id":32327,"original_language":"en","original_title":"Dreams That Money Can Buy","overview":"","popularity":3.753,"poster_path":"/gHtSimQF8HLpTGrNPP4bOLol1Wq.jpg","release_date":"1947-09-01","title":"Dreams That Money Can Buy","video":false,"vote_average":6.4,"vote_count":17,"character":"Theatre Extra (uncredited)","credit_id":"602ee24f1a934f00411df6f5","order":4},{"adult":false,"backdrop_path":"/1sSdTdzQDisjN8Tz5DPis19JKSL.jpg","genre_ids":[99,36],"id":888492,"original_language":"es","original_title":"La naranja prohibida","overview":"","popularity":5.214,"poster_path":"/rJ6SuyICUA24gPaKPhSp0nFIFDK.jpg","release_date":"2021-10-23","title":"La naranja prohibida","video":false,"vote_average":5.0,"vote_count":11,"character":"Self (archive footage)","credit_id":"618ccd2ecca7de00298cfac2","order":12},{"adult":false,"backdrop_path":null,"genre_ids":[99],"id":548051,"original_language":"en","original_title":"Secrets of British Animation","overview":"","popularity":1.528,"poster_path":"/lqUBSFQyLfMu1SaViEGhZ25Ea16.jpg","release_date":"2018-11-19","title":"Secrets of British Animation","video":false,"vote_average":6.0,"vote_count":1,"character":"Self (archive Footage)","credit_id":"61d307b722f5d7001f9ad891","order":13},{"adult":false,"backdrop_path":"/oC8JY6ngeDByxJRpjfHvXYd0Hv1.jpg","genre_ids":[99],"id":699744,"original_language":"en","original_title":"'2001: A Space Odyssey' – What Is Out There?","overview":"","popularity":2.496,"poster_path":"/338jc4NPpautvmovhCdfLdqczJs.jpg","release_date":"2007-10-23","title":"'2001: A Space Odyssey' – What Is Out There?","video":false,"vote_average":0.0,"vote_count":0,"character":"Self (archive footage)","credit_id":"6290e682ed2ac216ba108025","order":2},{"adult":false,"backdrop_path":null,"genre_ids":[99],"id":117604,"original_language":"en","original_title":"Edge of Outside","overview":"","popularity":4.988,"poster_path":"/aR0WqxNM0P9qxmdOZAdSxiSeVW0.jpg","release_date":"2006-06-11","title":"Edge of Outside","video":false,"vote_average":5.8,"vote_count":4,"character":"Self (archive footage)","credit_id":"62f690545c564e0083211b0e","order":39},{"adult":false,"backdrop_path":"/vYA4qUPWY0EbjpcIXAL4h4pVmTC.jpg","genre_ids":[18,53,9648],"id":345,"original_language":"en","original_title":"Eyes Wide Shut","overview":"Conviés à une soirée donnée par leur ami Victor Ziegler, le docteur William « Bill » Harford et son épouse Alice font, chacun de son côté, l'objet de tentatives de séduction plutôt osées. L'un et l'autre résistent à la tentation. Cependant, le lendemain, Alice avoue à son mari qu'elle a naguère songé à le tromper et regrette aujourd'hui de ne pas être passée à l'acte. Très ébranlé par cette révélation, William se rend chez une patiente, une jeune femme vulnérable qui vient de perdre son père. Celle-ci, contre toute attente, lui déclare sa flamme. De plus en plus perturbé, il choisit de s'enfuir. Dans la rue, il se fait accoster par une jeune prostituée, Domino, qui l'entraîne chez elle…","popularity":233.256,"poster_path":"/zrkNeLqUBm6bE2cqY5SBiM6LIf8.jpg","release_date":"1999-07-16","title":"Eyes Wide Shut","video":false,"vote_average":7.481,"vote_count":5916,"character":"Man at Café Sonata (uncredited)","credit_id":"63babcbea6e2d20083e157f4","order":79},{"adult":false,"backdrop_path":"/w5IDXtifKntw0ajv2co7jFlTQDM.jpg","genre_ids":[878,9648,12],"id":62,"original_language":"en","original_title":"2001: A Space Odyssey","overview":"Aux temps préhistoriques, une petite tribu d’hommes‐singes installée au milieu de rochers arides lutte difficilement pour la vie. Un matin, ils trouvent devant eux une mystérieuse dalle noire monolithique. L’un des singes touche la pierre et apprend alors à se servir d’un os de quadrupède pour tuer ses ennemis. Quatre millions d’années plus tard, en 2001, un savant de l’espace, le Dr Heywood Floyd, débarque sur la lune pour examiner une dalle noire semblable à celle des singes, qui était enterrée sous la surface de l’astre. Selon les premières observations, l’objet émettrait un signal mystérieux…","popularity":382.801,"poster_path":"/jNSk4dXs1cHu0SoLxmmZ2W6CYKl.jpg","release_date":"1968-04-02","title":"2001 : L'Odyssée de l'Espace","video":false,"vote_average":8.078,"vote_count":11108,"character":"(voice) (uncredited)","credit_id":"63d005060d2f5301d9a5cfc9","order":60},{"adult":false,"backdrop_path":null,"genre_ids":[99],"id":1083609,"original_language":"en","original_title":"James Mason: The Star They Loved to Hate","overview":"","popularity":4.07,"poster_path":"/iaiS5ezh616hvkKEOxxzRow9pAp.jpg","release_date":"1984-01-01","title":"James Mason: The Star They Loved to Hate","video":false,"vote_average":0.0,"vote_count":0,"character":"Self - 'Lolita' premiere (archive footage) (uncredited)","credit_id":"63e1ca83528b2e007d5e907a","order":11},{"adult":false,"backdrop_path":"/fNlbSr5xOFYAwR2A3pSyElTZOMp.jpg","genre_ids":[99],"id":399504,"original_language":"it","original_title":"S is for Stanley","overview":"Ce film relate la vie complexe du célèbre cinéaste Stanley Kubrick, à travers le regard de son chauffeur de longue date, Emilio D'Alessandro.","popularity":7.683,"poster_path":"/jk1FQFb1OIyEQnpB2OZOoQcj5Rs.jpg","release_date":"2016-05-30","title":"S is for Stanley","video":false,"vote_average":7.5,"vote_count":81,"character":"Self (archive footage)","credit_id":"659546940e64af1a3b8c1998","order":1},{"adult":false,"backdrop_path":"/3mhqxlsfSYGIKXHqBI4tQf2iNfx.jpg","genre_ids":[99,36],"id":595841,"original_language":"en","original_title":"Making Waves: The Art of Cinematic Sound","overview":"L'histoire du son au cinéma, racontée par des concepteurs sonores légendaires et des cinéastes visionnaires.","popularity":10.577,"poster_path":"/sdxXboU36GQHppAVDzyKbT8fYH2.jpg","release_date":"2019-10-25","title":"Making waves : la magie du son au cinéma","video":false,"vote_average":6.788,"vote_count":66,"character":"Self (archive footage)","credit_id":"65b0b7db2fe2fa01723cb484","order":62},{"adult":false,"backdrop_path":"/mK4fXD7JjwjOp407D2IpKwE8wjM.jpg","genre_ids":[18,53],"id":1247782,"original_language":"en","original_title":"The Day It Happened","overview":"","popularity":1.712,"poster_path":"/6nttVbjQX90x2PyjVRYHDdNrRPq.jpg","release_date":"2002-03-11","title":"The Day It Happened","video":false,"vote_average":0.0,"vote_count":0,"character":"Self (archive footage)","credit_id":"65d51ca0fdf8b7017cc6318c","order":4}],"crew":[{"adult":false,"backdrop_path":"/w5IDXtifKntw0ajv2co7jFlTQDM.jpg","genre_ids":[878,9648,12],"id":62,"original_language":"en","original_title":"2001: A Space Odyssey","overview":"Aux temps préhistoriques, une petite tribu d’hommes‐singes installée au milieu de rochers arides lutte difficilement pour la vie. Un matin, ils trouvent devant eux une mystérieuse dalle noire monolithique. L’un des singes touche la pierre et apprend alors à se servir d’un os de quadrupède pour tuer ses ennemis. Quatre millions d’années plus tard, en 2001, un savant de l’espace, le Dr Heywood Floyd, débarque sur la lune pour examiner une dalle noire semblable à celle des singes, qui était enterrée sous la surface de l’astre. Selon les premières observations, l’objet émettrait un signal mystérieux…","popularity":382.801,"poster_path":"/jNSk4dXs1cHu0SoLxmmZ2W6CYKl.jpg","release_date":"1968-04-02","title":"2001 : L'Odyssée de l'Espace","video":false,"vote_average":8.078,"vote_count":11108,"credit_id":"52fe4212c3a36847f8001a05","department":"Production","job":"Producer"},{"adult":false,"backdrop_path":"/w5IDXtifKntw0ajv2co7jFlTQDM.jpg","genre_ids":[878,9648,12],"id":62,"original_language":"en","original_title":"2001: A Space Odyssey","overview":"Aux temps préhistoriques, une petite tribu d’hommes‐singes installée au milieu de rochers arides lutte difficilement pour la vie. Un matin, ils trouvent devant eux une mystérieuse dalle noire monolithique. L’un des singes touche la pierre et apprend alors à se servir d’un os de quadrupède pour tuer ses ennemis. Quatre millions d’années plus tard, en 2001, un savant de l’espace, le Dr Heywood Floyd, débarque sur la lune pour examiner une dalle noire semblable à celle des singes, qui était enterrée sous la surface de l’astre. Selon les premières observations, l’objet émettrait un signal mystérieux…","popularity":382.801,"poster_path":"/jNSk4dXs1cHu0SoLxmmZ2W6CYKl.jpg","release_date":"1968-04-02","title":"2001 : L'Odyssée de l'Espace","video":false,"vote_average":8.078,"vote_count":11108,"credit_id":"52fe4212c3a36847f8001a0b","department":"Writing","job":"Screenplay"},{"adult":false,"backdrop_path":"/nLFxvLokHe3bQmrmAfljIfax2jQ.jpg","genre_ids":[878,80],"id":185,"original_language":"en","original_title":"A Clockwork Orange","overview":"Au XXIe siècle, où règnent la violence et le sexe, Alex, jeune chef de bande, exerce avec sadisme une terreur aveugle. Après son emprisonnement, des psychanalystes l'emploient comme cobaye dans des expériences destinées à juguler la criminalité…","popularity":52.062,"poster_path":"/n2oKNiEq9DZljqs6xsxs8hnsW9p.jpg","release_date":"1971-12-19","title":"Orange Mécanique","video":false,"vote_average":8.206,"vote_count":12482,"credit_id":"52fe4224c3a36847f80071e1","department":"Writing","job":"Screenplay"},{"adult":false,"backdrop_path":"/nLFxvLokHe3bQmrmAfljIfax2jQ.jpg","genre_ids":[878,80],"id":185,"original_language":"en","original_title":"A Clockwork Orange","overview":"Au XXIe siècle, où règnent la violence et le sexe, Alex, jeune chef de bande, exerce avec sadisme une terreur aveugle. Après son emprisonnement, des psychanalystes l'emploient comme cobaye dans des expériences destinées à juguler la criminalité…","popularity":52.062,"poster_path":"/n2oKNiEq9DZljqs6xsxs8hnsW9p.jpg","release_date":"1971-12-19","title":"Orange Mécanique","video":false,"vote_average":8.206,"vote_count":12482,"credit_id":"52fe4224c3a36847f80071db","department":"Directing","job":"Director"},{"adult":false,"backdrop_path":"/nLFxvLokHe3bQmrmAfljIfax2jQ.jpg","genre_ids":[878,80],"id":185,"original_language":"en","original_title":"A Clockwork Orange","overview":"Au XXIe siècle, où règnent la violence et le sexe, Alex, jeune chef de bande, exerce avec sadisme une terreur aveugle. Après son emprisonnement, des psychanalystes l'emploient comme cobaye dans des expériences destinées à juguler la criminalité…","popularity":52.062,"poster_path":"/n2oKNiEq9DZljqs6xsxs8hnsW9p.jpg","release_date":"1971-12-19","title":"Orange Mécanique","video":false,"vote_average":8.206,"vote_count":12482,"credit_id":"52fe4224c3a36847f800721f","department":"Production","job":"Producer"},{"adult":false,"backdrop_path":"/dY0suaAdGpOqh7JkLeIN6lT7k9d.jpg","genre_ids":[80,53],"id":247,"original_language":"en","original_title":"The Killing","overview":"Une bande de gangsters organisent le hold-up de la caisse des paris lors d'une course de chevaux…","popularity":48.013,"poster_path":"/wV8u4JEUEcqXVlqUuzuJL9BPUT4.jpg","release_date":"1956-06-06","title":"L'Ultime Razzia","video":false,"vote_average":7.665,"vote_count":1445,"credit_id":"52fe422cc3a36847f8009c91","department":"Writing","job":"Screenplay"},{"adult":false,"backdrop_path":"/dY0suaAdGpOqh7JkLeIN6lT7k9d.jpg","genre_ids":[80,53],"id":247,"original_language":"en","original_title":"The Killing","overview":"Une bande de gangsters organisent le hold-up de la caisse des paris lors d'une course de chevaux…","popularity":48.013,"poster_path":"/wV8u4JEUEcqXVlqUuzuJL9BPUT4.jpg","release_date":"1956-06-06","title":"L'Ultime Razzia","video":false,"vote_average":7.665,"vote_count":1445,"credit_id":"52fe422cc3a36847f8009c85","department":"Directing","job":"Director"},{"adult":false,"backdrop_path":"/vYA4qUPWY0EbjpcIXAL4h4pVmTC.jpg","genre_ids":[18,53,9648],"id":345,"original_language":"en","original_title":"Eyes Wide Shut","overview":"Conviés à une soirée donnée par leur ami Victor Ziegler, le docteur William « Bill » Harford et son épouse Alice font, chacun de son côté, l'objet de tentatives de séduction plutôt osées. L'un et l'autre résistent à la tentation. Cependant, le lendemain, Alice avoue à son mari qu'elle a naguère songé à le tromper et regrette aujourd'hui de ne pas être passée à l'acte. Très ébranlé par cette révélation, William se rend chez une patiente, une jeune femme vulnérable qui vient de perdre son père. Celle-ci, contre toute attente, lui déclare sa flamme. De plus en plus perturbé, il choisit de s'enfuir. Dans la rue, il se fait accoster par une jeune prostituée, Domino, qui l'entraîne chez elle…","popularity":233.256,"poster_path":"/zrkNeLqUBm6bE2cqY5SBiM6LIf8.jpg","release_date":"1999-07-16","title":"Eyes Wide Shut","video":false,"vote_average":7.481,"vote_count":5916,"credit_id":"52fe423bc3a36847f800df51","department":"Writing","job":"Screenplay"},{"adult":false,"backdrop_path":"/vYA4qUPWY0EbjpcIXAL4h4pVmTC.jpg","genre_ids":[18,53,9648],"id":345,"original_language":"en","original_title":"Eyes Wide Shut","overview":"Conviés à une soirée donnée par leur ami Victor Ziegler, le docteur William « Bill » Harford et son épouse Alice font, chacun de son côté, l'objet de tentatives de séduction plutôt osées. L'un et l'autre résistent à la tentation. Cependant, le lendemain, Alice avoue à son mari qu'elle a naguère songé à le tromper et regrette aujourd'hui de ne pas être passée à l'acte. Très ébranlé par cette révélation, William se rend chez une patiente, une jeune femme vulnérable qui vient de perdre son père. Celle-ci, contre toute attente, lui déclare sa flamme. De plus en plus perturbé, il choisit de s'enfuir. Dans la rue, il se fait accoster par une jeune prostituée, Domino, qui l'entraîne chez elle…","popularity":233.256,"poster_path":"/zrkNeLqUBm6bE2cqY5SBiM6LIf8.jpg","release_date":"1999-07-16","title":"Eyes Wide Shut","video":false,"vote_average":7.481,"vote_count":5916,"credit_id":"52fe423bc3a36847f800df45","department":"Directing","job":"Director"},{"adult":false,"backdrop_path":"/vYA4qUPWY0EbjpcIXAL4h4pVmTC.jpg","genre_ids":[18,53,9648],"id":345,"original_language":"en","original_title":"Eyes Wide Shut","overview":"Conviés à une soirée donnée par leur ami Victor Ziegler, le docteur William « Bill » Harford et son épouse Alice font, chacun de son côté, l'objet de tentatives de séduction plutôt osées. L'un et l'autre résistent à la tentation. Cependant, le lendemain, Alice avoue à son mari qu'elle a naguère songé à le tromper et regrette aujourd'hui de ne pas être passée à l'acte. Très ébranlé par cette révélation, William se rend chez une patiente, une jeune femme vulnérable qui vient de perdre son père. Celle-ci, contre toute attente, lui déclare sa flamme. De plus en plus perturbé, il choisit de s'enfuir. Dans la rue, il se fait accoster par une jeune prostituée, Domino, qui l'entraîne chez elle…","popularity":233.256,"poster_path":"/zrkNeLqUBm6bE2cqY5SBiM6LIf8.jpg","release_date":"1999-07-16","title":"Eyes Wide Shut","video":false,"vote_average":7.481,"vote_count":5916,"credit_id":"52fe423bc3a36847f800df5d","department":"Production","job":"Producer"},{"adult":false,"backdrop_path":"/mKEmuB7diOa7Ef0tJSGQ3fYJnNe.jpg","genre_ids":[18,10752],"id":600,"original_language":"en","original_title":"Full Metal Jacket","overview":"Pendant la guerre du Viêt Nam, la préparation et l’entraînement d’un groupe de jeunes marines, jusqu’au terrible baptême du feu et la sanglante offensive du Tết à Hue, en 1968.","popularity":42.983,"poster_path":"/cShwwkz4gBBIRj8yFy8TP2tEWZ4.jpg","release_date":"1987-06-26","title":"Full Metal Jacket","video":false,"vote_average":8.133,"vote_count":10126,"credit_id":"52fe425ac3a36847f8017cb7","department":"Directing","job":"Director"},{"adult":false,"backdrop_path":"/mKEmuB7diOa7Ef0tJSGQ3fYJnNe.jpg","genre_ids":[18,10752],"id":600,"original_language":"en","original_title":"Full Metal Jacket","overview":"Pendant la guerre du Viêt Nam, la préparation et l’entraînement d’un groupe de jeunes marines, jusqu’au terrible baptême du feu et la sanglante offensive du Tết à Hue, en 1968.","popularity":42.983,"poster_path":"/cShwwkz4gBBIRj8yFy8TP2tEWZ4.jpg","release_date":"1987-06-26","title":"Full Metal Jacket","video":false,"vote_average":8.133,"vote_count":10126,"credit_id":"52fe425ac3a36847f8017cc9","department":"Writing","job":"Screenplay"},{"adult":false,"backdrop_path":"/mKEmuB7diOa7Ef0tJSGQ3fYJnNe.jpg","genre_ids":[18,10752],"id":600,"original_language":"en","original_title":"Full Metal Jacket","overview":"Pendant la guerre du Viêt Nam, la préparation et l’entraînement d’un groupe de jeunes marines, jusqu’au terrible baptême du feu et la sanglante offensive du Tết à Hue, en 1968.","popularity":42.983,"poster_path":"/cShwwkz4gBBIRj8yFy8TP2tEWZ4.jpg","release_date":"1987-06-26","title":"Full Metal Jacket","video":false,"vote_average":8.133,"vote_count":10126,"credit_id":"52fe425ac3a36847f8017cd5","department":"Production","job":"Producer"},{"adult":false,"backdrop_path":"/mmd1HnuvAzFc4iuVJcnBrhDNEKr.jpg","genre_ids":[27,53],"id":694,"original_language":"en","original_title":"The Shining","overview":"Jack Torrance, gardien d’un hôtel fermé l’hiver, sa femme et son fils Danny s’apprêtent à vivre de longs mois de solitude. Danny, qui possède un don de médium, le «Shining», est effrayé à l’idée d’habiter ce lieu, théâtre marqué par de terribles événements passés…","popularity":99.674,"poster_path":"/gwCpaR7v1imLPBSl31X0OuYoysH.jpg","release_date":"1980-05-23","title":"Shining","video":false,"vote_average":8.217,"vote_count":16938,"credit_id":"52fe426bc3a36847f801d3b3","department":"Production","job":"Producer"},{"adult":false,"backdrop_path":"/mmd1HnuvAzFc4iuVJcnBrhDNEKr.jpg","genre_ids":[27,53],"id":694,"original_language":"en","original_title":"The Shining","overview":"Jack Torrance, gardien d’un hôtel fermé l’hiver, sa femme et son fils Danny s’apprêtent à vivre de longs mois de solitude. Danny, qui possède un don de médium, le «Shining», est effrayé à l’idée d’habiter ce lieu, théâtre marqué par de terribles événements passés…","popularity":99.674,"poster_path":"/gwCpaR7v1imLPBSl31X0OuYoysH.jpg","release_date":"1980-05-23","title":"Shining","video":false,"vote_average":8.217,"vote_count":16938,"credit_id":"52fe426bc3a36847f801d3a1","department":"Writing","job":"Screenplay"},{"adult":false,"backdrop_path":"/sTp8K0SfcC2RQef1Tu160z3niHO.jpg","genre_ids":[35,10752],"id":935,"original_language":"en","original_title":"Dr. Strangelove or: How I Learned to Stop Worrying and Love the Bomb","overview":"Le général Jack Ripper, convaincu que les Russes ont décidé d'empoisonner l'eau potable des États-Unis, lance sur l'URSS une offensive de bombardiers B-52 en ayant pris soin d'isoler la base aérienne de Burpelson du reste du monde. Pendant ce temps, Muffley, le Président des États-Unis, convoque l'état-major militaire dans la salle d'opérations du Pentagone et tente de rétablir la situation.","popularity":46.431,"poster_path":"/3g1CRHeMVLFVM2dcXasu3kBw4qV.jpg","release_date":"1964-01-29","title":"Docteur Folamour","video":false,"vote_average":8.123,"vote_count":5397,"credit_id":"52fe4290c3a36847f8028785","department":"Production","job":"Producer"},{"adult":false,"backdrop_path":"/sTp8K0SfcC2RQef1Tu160z3niHO.jpg","genre_ids":[35,10752],"id":935,"original_language":"en","original_title":"Dr. Strangelove or: How I Learned to Stop Worrying and Love the Bomb","overview":"Le général Jack Ripper, convaincu que les Russes ont décidé d'empoisonner l'eau potable des États-Unis, lance sur l'URSS une offensive de bombardiers B-52 en ayant pris soin d'isoler la base aérienne de Burpelson du reste du monde. Pendant ce temps, Muffley, le Président des États-Unis, convoque l'état-major militaire dans la salle d'opérations du Pentagone et tente de rétablir la situation.","popularity":46.431,"poster_path":"/3g1CRHeMVLFVM2dcXasu3kBw4qV.jpg","release_date":"1964-01-29","title":"Docteur Folamour","video":false,"vote_average":8.123,"vote_count":5397,"credit_id":"52fe4290c3a36847f802876d","department":"Directing","job":"Director"},{"adult":false,"backdrop_path":"/354kfjVb96mtFALMhBE6jzHGiA2.jpg","genre_ids":[10752,18,36],"id":975,"original_language":"en","original_title":"Paths of Glory","overview":"En 1916, durant la Première Guerre mondiale, le général français Broulard ordonne au général Mireau de lancer une offensive suicidaire contre une position allemande imprenable, surnommée la « Fourmilière ». Au moment de l'attaque, les soldats tombent par dizaines et leurs compagnons, épuisés, refusent d'avancer…","popularity":35.175,"poster_path":"/jqSEs0Umv1ZbMt50UqA4zkAhvsK.jpg","release_date":"1957-10-25","title":"Les Sentiers de la Gloire","video":false,"vote_average":8.27,"vote_count":2765,"credit_id":"52fe4295c3a36847f8029eb7","department":"Directing","job":"Director"},{"adult":false,"backdrop_path":"/9caD0fGCrp96JTFFeGyI0CGNj7.jpg","genre_ids":[36,10752,18,12],"id":967,"original_language":"en","original_title":"Spartacus","overview":"Italie, 73 av. J.C. Esclave devenu gladiateur, Spartacus est épargné par un de ses compagnons d'infortune dans un combat à mort. Ce répit soulève en lui plus que jamais le souffle de la révolte, et après avoir brisé ses chaînes, il enjoint les autres esclaves à faire de même. Rapidement à la tête d'une colossale armée, Spartacus entend rejoindre le port de Brides au sud du pays pour prendre la mer à bord des navires ciliciens. Mais l'Empire romain ne l'entend pas de cette oreille et lance ses légions à la poursuite des esclaves révoltés…","popularity":54.351,"poster_path":"/7jIkNQenhZdiGRcwMk8w9KhwFi6.jpg","release_date":"1960-10-13","title":"Spartacus","video":false,"vote_average":7.548,"vote_count":2060,"credit_id":"52fe4294c3a36847f8029cc9","department":"Directing","job":"Director"},{"adult":false,"backdrop_path":"/354kfjVb96mtFALMhBE6jzHGiA2.jpg","genre_ids":[10752,18,36],"id":975,"original_language":"en","original_title":"Paths of Glory","overview":"En 1916, durant la Première Guerre mondiale, le général français Broulard ordonne au général Mireau de lancer une offensive suicidaire contre une position allemande imprenable, surnommée la « Fourmilière ». Au moment de l'attaque, les soldats tombent par dizaines et leurs compagnons, épuisés, refusent d'avancer…","popularity":35.175,"poster_path":"/jqSEs0Umv1ZbMt50UqA4zkAhvsK.jpg","release_date":"1957-10-25","title":"Les Sentiers de la Gloire","video":false,"vote_average":8.27,"vote_count":2765,"credit_id":"52fe4295c3a36847f8029ec3","department":"Writing","job":"Screenplay"},{"adult":false,"backdrop_path":"/sTp8K0SfcC2RQef1Tu160z3niHO.jpg","genre_ids":[35,10752],"id":935,"original_language":"en","original_title":"Dr. Strangelove or: How I Learned to Stop Worrying and Love the Bomb","overview":"Le général Jack Ripper, convaincu que les Russes ont décidé d'empoisonner l'eau potable des États-Unis, lance sur l'URSS une offensive de bombardiers B-52 en ayant pris soin d'isoler la base aérienne de Burpelson du reste du monde. Pendant ce temps, Muffley, le Président des États-Unis, convoque l'état-major militaire dans la salle d'opérations du Pentagone et tente de rétablir la situation.","popularity":46.431,"poster_path":"/3g1CRHeMVLFVM2dcXasu3kBw4qV.jpg","release_date":"1964-01-29","title":"Docteur Folamour","video":false,"vote_average":8.123,"vote_count":5397,"credit_id":"52fe4290c3a36847f8028773","department":"Writing","job":"Screenplay"},{"adult":false,"backdrop_path":"/7iFieVSvFizrGMRsxwXedBWqw4g.jpg","genre_ids":[53,80,18],"id":10056,"original_language":"en","original_title":"Killer's Kiss","overview":"Après une défaite sur le ring dans un match officiel important, Davey Gordon défend une entraîneuse de dancing, Gloria, malmenée par son patron Vincent Rapallo. Les deux jeunes gens qui habitent dans le même voisinage, sympathisent et tombent amoureux. Gloria décide alors de quitter son travail pour fuir sa condition et son employeur. Ce dernier, épris d'elle, tente de l'en empêcher en éliminant Davey qui se retrouve ainsi confronté aux hommes de main de Rapallo. S'ensuit une poursuite haletante avec une scène mémorable dans un entrepôt de mannequins.","popularity":11.461,"poster_path":"/wv6NthVN03Fi6uWBRTnVzGK6Tu2.jpg","release_date":"1955-10-01","title":"Le Baiser du tueur","video":false,"vote_average":6.4,"vote_count":514,"credit_id":"52fe43169251416c75002ee3","department":"Directing","job":"Director"},{"adult":false,"backdrop_path":"/e3o0Dwlzzpd4kJpOOJgVyMstnII.jpg","genre_ids":[18,10752,53],"id":10165,"original_language":"en","original_title":"Fear and Desire","overview":"Dans une guerre abstraite en terre inconnue, une patrouille militaire de quatre hommes, le lieutenant Corby, le sergent Mac et deux soldats, Fletcher et Sidney, se retrouvent derrière les lignes ennemies après que leur avion se soit écrasé. Ils avancent dans la forêt, surprennent deux militaires ennemis et les massacrent. Puis ils rencontrent une jeune fille et, craignant qu'elle ne les dénonce, l'attachent à un arbre. Pendant que ses trois camarades vont vers la rivière construire un radeau qui, espèrent-ils, les ramènera chez eux, Sidney garde la jeune femme. Il se révèle alors avoir l'esprit dérangé, autant à cause des violences de la guerre que de son désir naissant envers la prisonnière...","popularity":10.353,"poster_path":"/mj7CDh6d5nJDDmEhd0ft6s3L8CM.jpg","release_date":"1953-03-31","title":"Fear and Desire","video":false,"vote_average":5.5,"vote_count":472,"credit_id":"52fe43399251416c750083df","department":"Directing","job":"Director"},{"adult":false,"backdrop_path":"/ef6SvWbSfCFlKodJZqpIaTvsRRP.jpg","genre_ids":[18,10749,10752],"id":3175,"original_language":"en","original_title":"Barry Lyndon","overview":"Chassé de son Irlande natale après une série d'exactions et d'inconvenances, Redmond Barry s'engage dans l'armée britannique et combat les Prussiens. Le métier des armes lui devient vite insupportable et il déserte. Capturé par l'ennemi, le jeune homme, ambitieux mais naïf, ne doit sa survie qu'à son empressement à servir ses nouveaux maîtres. La guerre finie, Redmond devient espion, puis joueur professionnel. Il fréquente la haute société, dont il apprend les usages et les bonnes manières. Ce talent lui permet de conquérir le cœur d'une jeune veuve, la comtesse de Lyndon, dont le fils, lord Bullingdon, lui voue bientôt la plus vive animosité…","popularity":25.473,"poster_path":"/prwtTDfRbwdNOzjURTabW3UYW0O.jpg","release_date":"1975-12-18","title":"Barry Lyndon","video":false,"vote_average":8.004,"vote_count":2698,"credit_id":"52fe438dc3a36847f805cca3","department":"Directing","job":"Director"},{"adult":false,"backdrop_path":"/ef6SvWbSfCFlKodJZqpIaTvsRRP.jpg","genre_ids":[18,10749,10752],"id":3175,"original_language":"en","original_title":"Barry Lyndon","overview":"Chassé de son Irlande natale après une série d'exactions et d'inconvenances, Redmond Barry s'engage dans l'armée britannique et combat les Prussiens. Le métier des armes lui devient vite insupportable et il déserte. Capturé par l'ennemi, le jeune homme, ambitieux mais naïf, ne doit sa survie qu'à son empressement à servir ses nouveaux maîtres. La guerre finie, Redmond devient espion, puis joueur professionnel. Il fréquente la haute société, dont il apprend les usages et les bonnes manières. Ce talent lui permet de conquérir le cœur d'une jeune veuve, la comtesse de Lyndon, dont le fils, lord Bullingdon, lui voue bientôt la plus vive animosité…","popularity":25.473,"poster_path":"/prwtTDfRbwdNOzjURTabW3UYW0O.jpg","release_date":"1975-12-18","title":"Barry Lyndon","video":false,"vote_average":8.004,"vote_count":2698,"credit_id":"52fe438dc3a36847f805cca9","department":"Writing","job":"Screenplay"},{"adult":false,"backdrop_path":"/ef6SvWbSfCFlKodJZqpIaTvsRRP.jpg","genre_ids":[18,10749,10752],"id":3175,"original_language":"en","original_title":"Barry Lyndon","overview":"Chassé de son Irlande natale après une série d'exactions et d'inconvenances, Redmond Barry s'engage dans l'armée britannique et combat les Prussiens. Le métier des armes lui devient vite insupportable et il déserte. Capturé par l'ennemi, le jeune homme, ambitieux mais naïf, ne doit sa survie qu'à son empressement à servir ses nouveaux maîtres. La guerre finie, Redmond devient espion, puis joueur professionnel. Il fréquente la haute société, dont il apprend les usages et les bonnes manières. Ce talent lui permet de conquérir le cœur d'une jeune veuve, la comtesse de Lyndon, dont le fils, lord Bullingdon, lui voue bientôt la plus vive animosité…","popularity":25.473,"poster_path":"/prwtTDfRbwdNOzjURTabW3UYW0O.jpg","release_date":"1975-12-18","title":"Barry Lyndon","video":false,"vote_average":8.004,"vote_count":2698,"credit_id":"52fe438dc3a36847f805ccb5","department":"Production","job":"Producer"},{"adult":false,"backdrop_path":"/7xqbG5FN1u2OIcuhhKahz9oejlY.jpg","genre_ids":[99],"id":45314,"original_language":"en","original_title":"The Seafarers","overview":"","popularity":8.312,"poster_path":"/rn2RpgGGPNMKp0QDoKgyLzavX8V.jpg","release_date":"1953-10-15","title":"The Seafarers","video":false,"vote_average":4.5,"vote_count":83,"credit_id":"52fe46bcc3a36847f810f44d","department":"Directing","job":"Director"},{"adult":false,"backdrop_path":"/lt1Lan9bmG29JjqaMad5tkRpCHJ.jpg","genre_ids":[99],"id":45966,"original_language":"en","original_title":"Day of the Fight","overview":"Interesting little short that works thanks to its pacing and shot variety.","popularity":6.857,"poster_path":"/4caX3IZkf7n2QCbxaJO3hyn0SCm.jpg","release_date":"1951-04-26","title":"Day of the Fight","video":false,"vote_average":5.771,"vote_count":146,"credit_id":"52fe46dcc3a36847f8116609","department":"Directing","job":"Director"},{"adult":false,"backdrop_path":"/5HisBYhc75h0DYXSMJWN1eFaxse.jpg","genre_ids":[99],"id":45970,"original_language":"en","original_title":"Flying Padre","overview":"Two days in the life of Reverend Fred Stadtmueller, a Catholic missionary whose New Mexico parish covers 400 square miles. For six years, he has been piloting his Piper Cub, called 'The Spirit of St. Joseph'. The reverend attends the funeral of a farmer, reconciles some children, breeds canaries, practices rifle shooting, then takes his airplane to fly a sick baby and its mother 40 miles away and transport them to an airport where an ambulance is waiting.","popularity":7.812,"poster_path":"/5aog5qVlMFakpogT1Nar9Z7gqq4.jpg","release_date":"1951-03-23","title":"Flying Padre","video":false,"vote_average":5.1,"vote_count":114,"credit_id":"52fe46dcc3a36847f81166bf","department":"Directing","job":"Director"},{"adult":false,"backdrop_path":"/lt1Lan9bmG29JjqaMad5tkRpCHJ.jpg","genre_ids":[99],"id":45966,"original_language":"en","original_title":"Day of the Fight","overview":"Interesting little short that works thanks to its pacing and shot variety.","popularity":6.857,"poster_path":"/4caX3IZkf7n2QCbxaJO3hyn0SCm.jpg","release_date":"1951-04-26","title":"Day of the Fight","video":false,"vote_average":5.771,"vote_count":146,"credit_id":"52fe46dcc3a36847f811660f","department":"Production","job":"Producer"},{"adult":false,"backdrop_path":"/e3o0Dwlzzpd4kJpOOJgVyMstnII.jpg","genre_ids":[18,10752,53],"id":10165,"original_language":"en","original_title":"Fear and Desire","overview":"Dans une guerre abstraite en terre inconnue, une patrouille militaire de quatre hommes, le lieutenant Corby, le sergent Mac et deux soldats, Fletcher et Sidney, se retrouvent derrière les lignes ennemies après que leur avion se soit écrasé. Ils avancent dans la forêt, surprennent deux militaires ennemis et les massacrent. Puis ils rencontrent une jeune fille et, craignant qu'elle ne les dénonce, l'attachent à un arbre. Pendant que ses trois camarades vont vers la rivière construire un radeau qui, espèrent-ils, les ramènera chez eux, Sidney garde la jeune femme. Il se révèle alors avoir l'esprit dérangé, autant à cause des violences de la guerre que de son désir naissant envers la prisonnière...","popularity":10.353,"poster_path":"/mj7CDh6d5nJDDmEhd0ft6s3L8CM.jpg","release_date":"1953-03-31","title":"Fear and Desire","video":false,"vote_average":5.5,"vote_count":472,"credit_id":"55d0b99ac3a3681bee007931","department":"Production","job":"Producer"},{"adult":false,"backdrop_path":"/e3o0Dwlzzpd4kJpOOJgVyMstnII.jpg","genre_ids":[18,10752,53],"id":10165,"original_language":"en","original_title":"Fear and Desire","overview":"Dans une guerre abstraite en terre inconnue, une patrouille militaire de quatre hommes, le lieutenant Corby, le sergent Mac et deux soldats, Fletcher et Sidney, se retrouvent derrière les lignes ennemies après que leur avion se soit écrasé. Ils avancent dans la forêt, surprennent deux militaires ennemis et les massacrent. Puis ils rencontrent une jeune fille et, craignant qu'elle ne les dénonce, l'attachent à un arbre. Pendant que ses trois camarades vont vers la rivière construire un radeau qui, espèrent-ils, les ramènera chez eux, Sidney garde la jeune femme. Il se révèle alors avoir l'esprit dérangé, autant à cause des violences de la guerre que de son désir naissant envers la prisonnière...","popularity":10.353,"poster_path":"/mj7CDh6d5nJDDmEhd0ft6s3L8CM.jpg","release_date":"1953-03-31","title":"Fear and Desire","video":false,"vote_average":5.5,"vote_count":472,"credit_id":"55d0b9cc925141319f008030","department":"Editing","job":"Editor"},{"adult":false,"backdrop_path":"/lt1Lan9bmG29JjqaMad5tkRpCHJ.jpg","genre_ids":[99],"id":45966,"original_language":"en","original_title":"Day of the Fight","overview":"Interesting little short that works thanks to its pacing and shot variety.","popularity":6.857,"poster_path":"/4caX3IZkf7n2QCbxaJO3hyn0SCm.jpg","release_date":"1951-04-26","title":"Day of the Fight","video":false,"vote_average":5.771,"vote_count":146,"credit_id":"55d0b196c3a3681bff007bde","department":"Camera","job":"Director of Photography"},{"adult":false,"backdrop_path":"/e3o0Dwlzzpd4kJpOOJgVyMstnII.jpg","genre_ids":[18,10752,53],"id":10165,"original_language":"en","original_title":"Fear and Desire","overview":"Dans une guerre abstraite en terre inconnue, une patrouille militaire de quatre hommes, le lieutenant Corby, le sergent Mac et deux soldats, Fletcher et Sidney, se retrouvent derrière les lignes ennemies après que leur avion se soit écrasé. Ils avancent dans la forêt, surprennent deux militaires ennemis et les massacrent. Puis ils rencontrent une jeune fille et, craignant qu'elle ne les dénonce, l'attachent à un arbre. Pendant que ses trois camarades vont vers la rivière construire un radeau qui, espèrent-ils, les ramènera chez eux, Sidney garde la jeune femme. Il se révèle alors avoir l'esprit dérangé, autant à cause des violences de la guerre que de son désir naissant envers la prisonnière...","popularity":10.353,"poster_path":"/mj7CDh6d5nJDDmEhd0ft6s3L8CM.jpg","release_date":"1953-03-31","title":"Fear and Desire","video":false,"vote_average":5.5,"vote_count":472,"credit_id":"55d0b9c392514131a5007a4c","department":"Camera","job":"Director of Photography"},{"adult":false,"backdrop_path":"/7xqbG5FN1u2OIcuhhKahz9oejlY.jpg","genre_ids":[99],"id":45314,"original_language":"en","original_title":"The Seafarers","overview":"","popularity":8.312,"poster_path":"/rn2RpgGGPNMKp0QDoKgyLzavX8V.jpg","release_date":"1953-10-15","title":"The Seafarers","video":false,"vote_average":4.5,"vote_count":83,"credit_id":"55d0cae1c3a36877570014d2","department":"Camera","job":"Director of Photography"},{"adult":false,"backdrop_path":"/354kfjVb96mtFALMhBE6jzHGiA2.jpg","genre_ids":[10752,18,36],"id":975,"original_language":"en","original_title":"Paths of Glory","overview":"En 1916, durant la Première Guerre mondiale, le général français Broulard ordonne au général Mireau de lancer une offensive suicidaire contre une position allemande imprenable, surnommée la « Fourmilière ». Au moment de l'attaque, les soldats tombent par dizaines et leurs compagnons, épuisés, refusent d'avancer…","popularity":35.175,"poster_path":"/jqSEs0Umv1ZbMt50UqA4zkAhvsK.jpg","release_date":"1957-10-25","title":"Les Sentiers de la Gloire","video":false,"vote_average":8.27,"vote_count":2765,"credit_id":"5706f1259251412b1400065c","department":"Camera","job":"Additional Photography"},{"adult":false,"backdrop_path":"/7iFieVSvFizrGMRsxwXedBWqw4g.jpg","genre_ids":[53,80,18],"id":10056,"original_language":"en","original_title":"Killer's Kiss","overview":"Après une défaite sur le ring dans un match officiel important, Davey Gordon défend une entraîneuse de dancing, Gloria, malmenée par son patron Vincent Rapallo. Les deux jeunes gens qui habitent dans le même voisinage, sympathisent et tombent amoureux. Gloria décide alors de quitter son travail pour fuir sa condition et son employeur. Ce dernier, épris d'elle, tente de l'en empêcher en éliminant Davey qui se retrouve ainsi confronté aux hommes de main de Rapallo. S'ensuit une poursuite haletante avec une scène mémorable dans un entrepôt de mannequins.","popularity":11.461,"poster_path":"/wv6NthVN03Fi6uWBRTnVzGK6Tu2.jpg","release_date":"1955-10-01","title":"Le Baiser du tueur","video":false,"vote_average":6.4,"vote_count":514,"credit_id":"57aa166492514111aa00156e","department":"Editing","job":"Editor"},{"adult":false,"backdrop_path":"/7iFieVSvFizrGMRsxwXedBWqw4g.jpg","genre_ids":[53,80,18],"id":10056,"original_language":"en","original_title":"Killer's Kiss","overview":"Après une défaite sur le ring dans un match officiel important, Davey Gordon défend une entraîneuse de dancing, Gloria, malmenée par son patron Vincent Rapallo. Les deux jeunes gens qui habitent dans le même voisinage, sympathisent et tombent amoureux. Gloria décide alors de quitter son travail pour fuir sa condition et son employeur. Ce dernier, épris d'elle, tente de l'en empêcher en éliminant Davey qui se retrouve ainsi confronté aux hommes de main de Rapallo. S'ensuit une poursuite haletante avec une scène mémorable dans un entrepôt de mannequins.","popularity":11.461,"poster_path":"/wv6NthVN03Fi6uWBRTnVzGK6Tu2.jpg","release_date":"1955-10-01","title":"Le Baiser du tueur","video":false,"vote_average":6.4,"vote_count":514,"credit_id":"57aa15ad92514111aa00153b","department":"Production","job":"Producer"},{"adult":false,"backdrop_path":"/7iFieVSvFizrGMRsxwXedBWqw4g.jpg","genre_ids":[53,80,18],"id":10056,"original_language":"en","original_title":"Killer's Kiss","overview":"Après une défaite sur le ring dans un match officiel important, Davey Gordon défend une entraîneuse de dancing, Gloria, malmenée par son patron Vincent Rapallo. Les deux jeunes gens qui habitent dans le même voisinage, sympathisent et tombent amoureux. Gloria décide alors de quitter son travail pour fuir sa condition et son employeur. Ce dernier, épris d'elle, tente de l'en empêcher en éliminant Davey qui se retrouve ainsi confronté aux hommes de main de Rapallo. S'ensuit une poursuite haletante avec une scène mémorable dans un entrepôt de mannequins.","popularity":11.461,"poster_path":"/wv6NthVN03Fi6uWBRTnVzGK6Tu2.jpg","release_date":"1955-10-01","title":"Le Baiser du tueur","video":false,"vote_average":6.4,"vote_count":514,"credit_id":"57aa15a0c3a368739f007db9","department":"Writing","job":"Story"},{"adult":false,"backdrop_path":"/7xqbG5FN1u2OIcuhhKahz9oejlY.jpg","genre_ids":[99],"id":45314,"original_language":"en","original_title":"The Seafarers","overview":"","popularity":8.312,"poster_path":"/rn2RpgGGPNMKp0QDoKgyLzavX8V.jpg","release_date":"1953-10-15","title":"The Seafarers","video":false,"vote_average":4.5,"vote_count":83,"credit_id":"5960f39392514121f00a150b","department":"Editing","job":"Editor"},{"adult":false,"backdrop_path":"/7xqbG5FN1u2OIcuhhKahz9oejlY.jpg","genre_ids":[99],"id":45314,"original_language":"en","original_title":"The Seafarers","overview":"","popularity":8.312,"poster_path":"/rn2RpgGGPNMKp0QDoKgyLzavX8V.jpg","release_date":"1953-10-15","title":"The Seafarers","video":false,"vote_average":4.5,"vote_count":83,"credit_id":"5960f39b9251410b860bf70c","department":"Sound","job":"Sound"},{"adult":false,"backdrop_path":"/w5IDXtifKntw0ajv2co7jFlTQDM.jpg","genre_ids":[878,9648,12],"id":62,"original_language":"en","original_title":"2001: A Space Odyssey","overview":"Aux temps préhistoriques, une petite tribu d’hommes‐singes installée au milieu de rochers arides lutte difficilement pour la vie. Un matin, ils trouvent devant eux une mystérieuse dalle noire monolithique. L’un des singes touche la pierre et apprend alors à se servir d’un os de quadrupède pour tuer ses ennemis. Quatre millions d’années plus tard, en 2001, un savant de l’espace, le Dr Heywood Floyd, débarque sur la lune pour examiner une dalle noire semblable à celle des singes, qui était enterrée sous la surface de l’astre. Selon les premières observations, l’objet émettrait un signal mystérieux…","popularity":382.801,"poster_path":"/jNSk4dXs1cHu0SoLxmmZ2W6CYKl.jpg","release_date":"1968-04-02","title":"2001 : L'Odyssée de l'Espace","video":false,"vote_average":8.078,"vote_count":11108,"credit_id":"5a874c109251410aae03fdf4","department":"Visual Effects","job":"Visual Effects"},{"adult":false,"backdrop_path":"/7iFieVSvFizrGMRsxwXedBWqw4g.jpg","genre_ids":[53,80,18],"id":10056,"original_language":"en","original_title":"Killer's Kiss","overview":"Après une défaite sur le ring dans un match officiel important, Davey Gordon défend une entraîneuse de dancing, Gloria, malmenée par son patron Vincent Rapallo. Les deux jeunes gens qui habitent dans le même voisinage, sympathisent et tombent amoureux. Gloria décide alors de quitter son travail pour fuir sa condition et son employeur. Ce dernier, épris d'elle, tente de l'en empêcher en éliminant Davey qui se retrouve ainsi confronté aux hommes de main de Rapallo. S'ensuit une poursuite haletante avec une scène mémorable dans un entrepôt de mannequins.","popularity":11.461,"poster_path":"/wv6NthVN03Fi6uWBRTnVzGK6Tu2.jpg","release_date":"1955-10-01","title":"Le Baiser du tueur","video":false,"vote_average":6.4,"vote_count":514,"credit_id":"5d2f94c46a300b2246a57ffb","department":"Sound","job":"Sound Editor"},{"adult":false,"backdrop_path":"/mmd1HnuvAzFc4iuVJcnBrhDNEKr.jpg","genre_ids":[27,53],"id":694,"original_language":"en","original_title":"The Shining","overview":"Jack Torrance, gardien d’un hôtel fermé l’hiver, sa femme et son fils Danny s’apprêtent à vivre de longs mois de solitude. Danny, qui possède un don de médium, le «Shining», est effrayé à l’idée d’habiter ce lieu, théâtre marqué par de terribles événements passés…","popularity":99.674,"poster_path":"/gwCpaR7v1imLPBSl31X0OuYoysH.jpg","release_date":"1980-05-23","title":"Shining","video":false,"vote_average":8.217,"vote_count":16938,"credit_id":"5e6586c6d35dea00110142e6","department":"Directing","job":"Director"},{"adult":false,"backdrop_path":"/w5IDXtifKntw0ajv2co7jFlTQDM.jpg","genre_ids":[878,9648,12],"id":62,"original_language":"en","original_title":"2001: A Space Odyssey","overview":"Aux temps préhistoriques, une petite tribu d’hommes‐singes installée au milieu de rochers arides lutte difficilement pour la vie. Un matin, ils trouvent devant eux une mystérieuse dalle noire monolithique. L’un des singes touche la pierre et apprend alors à se servir d’un os de quadrupède pour tuer ses ennemis. Quatre millions d’années plus tard, en 2001, un savant de l’espace, le Dr Heywood Floyd, débarque sur la lune pour examiner une dalle noire semblable à celle des singes, qui était enterrée sous la surface de l’astre. Selon les premières observations, l’objet émettrait un signal mystérieux…","popularity":382.801,"poster_path":"/jNSk4dXs1cHu0SoLxmmZ2W6CYKl.jpg","release_date":"1968-04-02","title":"2001 : L'Odyssée de l'Espace","video":false,"vote_average":8.078,"vote_count":11108,"credit_id":"5e8354893344c600182bbb4d","department":"Directing","job":"Director"},{"adult":false,"backdrop_path":"/5HisBYhc75h0DYXSMJWN1eFaxse.jpg","genre_ids":[99],"id":45970,"original_language":"en","original_title":"Flying Padre","overview":"Two days in the life of Reverend Fred Stadtmueller, a Catholic missionary whose New Mexico parish covers 400 square miles. For six years, he has been piloting his Piper Cub, called 'The Spirit of St. Joseph'. The reverend attends the funeral of a farmer, reconciles some children, breeds canaries, practices rifle shooting, then takes his airplane to fly a sick baby and its mother 40 miles away and transport them to an airport where an ambulance is waiting.","popularity":7.812,"poster_path":"/5aog5qVlMFakpogT1Nar9Z7gqq4.jpg","release_date":"1951-03-23","title":"Flying Padre","video":false,"vote_average":5.1,"vote_count":114,"credit_id":"5e94991dccb15f001571103c","department":"Camera","job":"Director of Photography"},{"adult":false,"backdrop_path":"/7iFieVSvFizrGMRsxwXedBWqw4g.jpg","genre_ids":[53,80,18],"id":10056,"original_language":"en","original_title":"Killer's Kiss","overview":"Après une défaite sur le ring dans un match officiel important, Davey Gordon défend une entraîneuse de dancing, Gloria, malmenée par son patron Vincent Rapallo. Les deux jeunes gens qui habitent dans le même voisinage, sympathisent et tombent amoureux. Gloria décide alors de quitter son travail pour fuir sa condition et son employeur. Ce dernier, épris d'elle, tente de l'en empêcher en éliminant Davey qui se retrouve ainsi confronté aux hommes de main de Rapallo. S'ensuit une poursuite haletante avec une scène mémorable dans un entrepôt de mannequins.","popularity":11.461,"poster_path":"/wv6NthVN03Fi6uWBRTnVzGK6Tu2.jpg","release_date":"1955-10-01","title":"Le Baiser du tueur","video":false,"vote_average":6.4,"vote_count":514,"credit_id":"5e9499448e87020013ce555f","department":"Camera","job":"Director of Photography"},{"adult":false,"backdrop_path":"/40JNQ4FOekM1LDgUC5mDcM8bZyl.jpg","genre_ids":[80,18,10749],"id":802,"original_language":"en","original_title":"Lolita","overview":"L'écrivain Humbert Humbert vient d'obtenir une chaire de littérature française à l'université de Ramsdale. Il trouve une chambre chez une jeune veuve, Charlotte Haze, qui tombe rapidement amoureuse de lui. Mais les yeux d'Humbert ne voient que Lolita, l'aguichante et troublante fille de Charlotte. Pour être sûr de rester toujours auprès de la jeune fille, il finit par céder aux multiples avances de sa mère, et accepte de l'épouser. Un accident vient à point nommé abréger la vie de Charlotte, au moment même où elle apprend la vérité sur les sentiments de Humbert. L'écrivain entraîne alors Lolita dans une folle passion qui les mènera jusqu'au meurtre…","popularity":41.443,"poster_path":"/oNTBCmVYgPNsGZXb3zMB8X5tp03.jpg","release_date":"1962-06-13","title":"Lolita","video":false,"vote_average":7.342,"vote_count":1971,"credit_id":"5eb5bdb5ca7ec6001f7979d3","department":"Directing","job":"Director"},{"adult":false,"backdrop_path":"/n7p6UTAZtkeoHkwCO42BEQaMFJY.jpg","genre_ids":[18,878,12],"id":644,"original_language":"en","original_title":"A.I. Artificial Intelligence","overview":"Dans un XXIe siècle où la fonte des glaces a submergé la majorité des terres habitables et provoqué famines et exodes, les robots sont devenus une composante essentielle de la vie quotidienne, et assurent désormais la plupart des tâches domestiques. Pourtant, le professeur Hobby veut aller encore plus loin en créant le premier androïde sensible : un enfant capable de développer un vaste répertoire d'émotions et de souvenirs. Peu après cette annonce, David, un robot de onze ans, fait son entrée chez Henry et Monica Swinton, un couple dont le jeune fils a été cryogénisé en attendant la découverte d'un remède pour guérir sa grave maladie. Bientôt abandonné par sa mère adoptive, David entame un périlleux voyage à la recherche de son identité et de sa part secrète d'humanité.","popularity":52.563,"poster_path":"/q9zvQ1WuriRlGDYu5Nip5N2vZRA.jpg","release_date":"2001-06-29","title":"A.I. Intelligence Artificielle","video":false,"vote_average":7.044,"vote_count":5950,"credit_id":"63e0ead4373ac2170994d2c6","department":"Writing","job":"Idea"},{"adult":false,"backdrop_path":"/354kfjVb96mtFALMhBE6jzHGiA2.jpg","genre_ids":[10752,18,36],"id":975,"original_language":"en","original_title":"Paths of Glory","overview":"En 1916, durant la Première Guerre mondiale, le général français Broulard ordonne au général Mireau de lancer une offensive suicidaire contre une position allemande imprenable, surnommée la « Fourmilière ». Au moment de l'attaque, les soldats tombent par dizaines et leurs compagnons, épuisés, refusent d'avancer…","popularity":35.175,"poster_path":"/jqSEs0Umv1ZbMt50UqA4zkAhvsK.jpg","release_date":"1957-10-25","title":"Les Sentiers de la Gloire","video":false,"vote_average":8.27,"vote_count":2765,"credit_id":"6524ad1d74507d00ff9bde41","department":"Production","job":"Executive Producer"}]},"external_ids":{"freebase_mid":"/m/06mn7","freebase_id":null,"imdb_id":"nm0000040","tvrage_id":null,"wikidata_id":"Q2001","facebook_id":null,"instagram_id":null,"tiktok_id":null,"twitter_id":null,"youtube_id":null},"images":{"profiles":[{"aspect_ratio":0.667,"height":3000,"iso_639_1":null,"file_path":"/yFT0VyIelI9aegZrsAwOG5iVP4v.jpg","vote_average":5.514,"vote_count":18,"width":2000},{"aspect_ratio":0.667,"height":1203,"iso_639_1":null,"file_path":"/exfQ6vXXq7rMS5YWb3B88PK39a1.jpg","vote_average":5.462,"vote_count":41,"width":802},{"aspect_ratio":0.667,"height":900,"iso_639_1":null,"file_path":"/4azoknQJpwC6L0ILxgvNgXUuNOr.jpg","vote_average":5.406,"vote_count":22,"width":600},{"aspect_ratio":0.667,"height":1500,"iso_639_1":null,"file_path":"/lpnyMWomTwper9duSLZCyFwJq3R.jpg","vote_average":5.046,"vote_count":14,"width":1000},{"aspect_ratio":0.667,"height":1200,"iso_639_1":null,"file_path":"/yHLMerei7324whA72UVt91Ed3Yt.jpg","vote_average":4.968,"vote_count":11,"width":800},{"aspect_ratio":0.665,"height":1024,"iso_639_1":null,"file_path":"/6K3ycyLeadkwMUPOCCOUr6OYY13.jpg","vote_average":4.898,"vote_count":10,"width":681},{"aspect_ratio":0.667,"height":1200,"iso_639_1":null,"file_path":"/clQ7fqFDWK3O4YlJ37bePAE3rZr.jpg","vote_average":4.898,"vote_count":10,"width":800}]}}